[
  {
    "experiment_id": "BOTTLE_BRAND_DEFENSE_BRAND",
    "experiment_name": "Truth or Dare - Brand Defense",
    "strategy_id": "BRAND_DEFENSE",
    "week_start": "2026-02-08",
    "sales": 1405.3,
    "ads_spend": 178.85,
    "total_orders": 47,
    "ads_orders": 19,
    "organic_orders": 28,
    "sessions": 696,
    "conv_rate": 2.73,
    "net_roas": 6.86,
    "organic_pct": 59.6
  },
  {
    "experiment_id": "BOTTLE_BRAND_DEFENSE_BRAND",
    "experiment_name": "Truth or Dare - Brand Defense",
    "strategy_id": "BRAND_DEFENSE",
    "week_start": "2026-02-15",
    "sales": 1166.1,
    "ads_spend": 159.76,
    "total_orders": 39,
    "ads_orders": 18,
    "organic_orders": 21,
    "sessions": 850,
    "conv_rate": 2.12,
    "net_roas": 6.3,
    "organic_pct": 53.8
  },
  {
    "experiment_id": "BOTTLE_BRAND_DEFENSE_BRAND",
    "experiment_name": "Truth or Dare - Brand Defense",
    "strategy_id": "BRAND_DEFENSE",
    "week_start": "2026-02-22",
    "sales": 807.3,
    "ads_spend": 321.47,
    "total_orders": 27,
    "ads_orders": 18,
    "organic_orders": 9,
    "sessions": 975,
    "conv_rate": 1.85,
    "net_roas": 1.51,
    "organic_pct": 33.3
  },
  {
    "experiment_id": "BOTTLE_BRAND_DEFENSE_BRAND",
    "experiment_name": "Truth or Dare - Brand Defense",
    "strategy_id": "BRAND_DEFENSE",
    "week_start": "2026-03-01",
    "sales": 747.5,
    "ads_spend": 231.51,
    "total_orders": 25,
    "ads_orders": 18,
    "organic_orders": 7,
    "sessions": 570,
    "conv_rate": 3.16,
    "net_roas": 2.23,
    "organic_pct": 28.0
  },
  {
    "experiment_id": "BOTTLE_PRODUCT_DEFENSE",
    "experiment_name": "Truth or Dare - Product Defense",
    "strategy_id": "PRODUCT_DEFENSE",
    "week_start": "2026-02-08",
    "sales": 1405.3,
    "ads_spend": 178.85,
    "total_orders": 47,
    "ads_orders": 19,
    "organic_orders": 28,
    "sessions": 696,
    "conv_rate": 2.73,
    "net_roas": 6.86,
    "organic_pct": 59.6
  },
  {
    "experiment_id": "BOTTLE_PRODUCT_DEFENSE",
    "experiment_name": "Truth or Dare - Product Defense",
    "strategy_id": "PRODUCT_DEFENSE",
    "week_start": "2026-02-15",
    "sales": 1166.1,
    "ads_spend": 159.76,
    "total_orders": 39,
    "ads_orders": 18,
    "organic_orders": 21,
    "sessions": 850,
    "conv_rate": 2.12,
    "net_roas": 6.3,
    "organic_pct": 53.8
  },
  {
    "experiment_id": "BOTTLE_PRODUCT_DEFENSE",
    "experiment_name": "Truth or Dare - Product Defense",
    "strategy_id": "PRODUCT_DEFENSE",
    "week_start": "2026-02-22",
    "sales": 807.3,
    "ads_spend": 321.47,
    "total_orders": 27,
    "ads_orders": 18,
    "organic_orders": 9,
    "sessions": 975,
    "conv_rate": 1.85,
    "net_roas": 1.51,
    "organic_pct": 33.3
  },
  {
    "experiment_id": "BOTTLE_PRODUCT_DEFENSE",
    "experiment_name": "Truth or Dare - Product Defense",
    "strategy_id": "PRODUCT_DEFENSE",
    "week_start": "2026-03-01",
    "sales": 747.5,
    "ads_spend": 231.51,
    "total_orders": 25,
    "ads_orders": 18,
    "organic_orders": 7,
    "sessions": 570,
    "conv_rate": 3.16,
    "net_roas": 2.23,
    "organic_pct": 28.0
  },
  {
    "experiment_id": "EXP001",
    "experiment_name": "SB Exact - Girls Journal Video",
    "strategy_id": "EXACT_BOOST",
    "week_start": "2025-12-28",
    "sales": 1022.69,
    "ads_spend": 342.61,
    "total_orders": 30,
    "ads_orders": 26,
    "organic_orders": 4,
    "sessions": 615,
    "conv_rate": 4.23,
    "net_roas": 1.98,
    "organic_pct": 13.3
  },
  {
    "experiment_id": "EXP001",
    "experiment_name": "SB Exact - Girls Journal Video",
    "strategy_id": "EXACT_BOOST",
    "week_start": "2026-01-04",
    "sales": 2540.23,
    "ads_spend": 763.82,
    "total_orders": 78,
    "ads_orders": 71,
    "organic_orders": 7,
    "sessions": 1678,
    "conv_rate": 4.23,
    "net_roas": 2.33,
    "organic_pct": 9.0
  },
  {
    "experiment_id": "EXP001",
    "experiment_name": "SB Exact - Girls Journal Video",
    "strategy_id": "EXACT_BOOST",
    "week_start": "2026-01-11",
    "sales": 3496.94,
    "ads_spend": 771.48,
    "total_orders": 100,
    "ads_orders": 80,
    "organic_orders": 20,
    "sessions": 1917,
    "conv_rate": 4.17,
    "net_roas": 3.53,
    "organic_pct": 20.0
  },
  {
    "experiment_id": "EXP001",
    "experiment_name": "SB Exact - Girls Journal Video",
    "strategy_id": "EXACT_BOOST",
    "week_start": "2026-01-18",
    "sales": 2738.17,
    "ads_spend": 1095.56,
    "total_orders": 83,
    "ads_orders": 89,
    "organic_orders": -6,
    "sessions": 2252,
    "conv_rate": 3.95,
    "net_roas": 1.5,
    "organic_pct": -7.2
  },
  {
    "experiment_id": "EXP001",
    "experiment_name": "SB Exact - Girls Journal Video",
    "strategy_id": "EXACT_BOOST",
    "week_start": "2026-01-25",
    "sales": 2276.31,
    "ads_spend": 736.47,
    "total_orders": 69,
    "ads_orders": 49,
    "organic_orders": 20,
    "sessions": 1816,
    "conv_rate": 2.7,
    "net_roas": 2.09,
    "organic_pct": 29.0
  },
  {
    "experiment_id": "EXP001",
    "experiment_name": "SB Exact - Girls Journal Video",
    "strategy_id": "EXACT_BOOST",
    "week_start": "2026-02-01",
    "sales": 2441.26,
    "ads_spend": 492.24,
    "total_orders": 72,
    "ads_orders": 55,
    "organic_orders": 17,
    "sessions": 1489,
    "conv_rate": 3.69,
    "net_roas": 3.96,
    "organic_pct": 23.6
  },
  {
    "experiment_id": "EXP001",
    "experiment_name": "SB Exact - Girls Journal Video",
    "strategy_id": "EXACT_BOOST",
    "week_start": "2026-02-08",
    "sales": 2771.16,
    "ads_spend": 572.07,
    "total_orders": 83,
    "ads_orders": 77,
    "organic_orders": 6,
    "sessions": 1351,
    "conv_rate": 5.7,
    "net_roas": 3.84,
    "organic_pct": 7.2
  },
  {
    "experiment_id": "EXP001",
    "experiment_name": "SB Exact - Girls Journal Video",
    "strategy_id": "EXACT_BOOST",
    "week_start": "2026-02-15",
    "sales": 1979.4,
    "ads_spend": 464.12,
    "total_orders": 59,
    "ads_orders": 46,
    "organic_orders": 13,
    "sessions": 694,
    "conv_rate": 6.63,
    "net_roas": 3.26,
    "organic_pct": 22.0
  },
  {
    "experiment_id": "EXP001_HOLIDAY_2025",
    "experiment_name": "SB Exact - Girls Journal Video (Holiday 2025)",
    "strategy_id": "EXACT_BOOST",
    "week_start": "2025-12-14",
    "sales": 34281.8,
    "ads_spend": 6770.31,
    "total_orders": 1018,
    "ads_orders": 828,
    "organic_orders": 190,
    "sessions": 8343,
    "conv_rate": 9.92,
    "net_roas": 4.06,
    "organic_pct": 18.7
  },
  {
    "experiment_id": "EXP001_HOLIDAY_2025",
    "experiment_name": "SB Exact - Girls Journal Video (Holiday 2025)",
    "strategy_id": "EXACT_BOOST",
    "week_start": "2025-12-21",
    "sales": 8521.1,
    "ads_spend": 1873.99,
    "total_orders": 251,
    "ads_orders": 157,
    "organic_orders": 94,
    "sessions": 3432,
    "conv_rate": 4.57,
    "net_roas": 3.55,
    "organic_pct": 37.5
  },
  {
    "experiment_id": "EXP001_HOLIDAY_2025",
    "experiment_name": "SB Exact - Girls Journal Video (Holiday 2025)",
    "strategy_id": "EXACT_BOOST",
    "week_start": "2025-12-28",
    "sales": 1513.4,
    "ads_spend": 338.92,
    "total_orders": 46,
    "ads_orders": 22,
    "organic_orders": 24,
    "sessions": 870,
    "conv_rate": 2.53,
    "net_roas": 3.47,
    "organic_pct": 52.2
  },
  {
    "experiment_id": "FRESH_BRAND_DEFENSE_BRAND",
    "experiment_name": "Fresh Collection - Brand Defense",
    "strategy_id": "BRAND_DEFENSE",
    "week_start": "2026-02-08",
    "sales": 2092.25,
    "ads_spend": 0.0,
    "total_orders": 42,
    "ads_orders": 0,
    "organic_orders": 42,
    "sessions": 618,
    "conv_rate": 0.0,
    "net_roas": null,
    "organic_pct": 100.0
  },
  {
    "experiment_id": "FRESH_BRAND_DEFENSE_BRAND",
    "experiment_name": "Fresh Collection - Brand Defense",
    "strategy_id": "BRAND_DEFENSE",
    "week_start": "2026-02-15",
    "sales": 1147.7,
    "ads_spend": 2.66,
    "total_orders": 23,
    "ads_orders": 0,
    "organic_orders": 23,
    "sessions": 468,
    "conv_rate": 0.0,
    "net_roas": 430.47,
    "organic_pct": 100.0
  },
  {
    "experiment_id": "FRESH_BRAND_DEFENSE_BRAND",
    "experiment_name": "Fresh Collection - Brand Defense",
    "strategy_id": "BRAND_DEFENSE",
    "week_start": "2026-02-22",
    "sales": 898.2,
    "ads_spend": 133.31,
    "total_orders": 18,
    "ads_orders": 6,
    "organic_orders": 12,
    "sessions": 538,
    "conv_rate": 1.12,
    "net_roas": 5.74,
    "organic_pct": 66.7
  },
  {
    "experiment_id": "FRESH_BRAND_DEFENSE_BRAND",
    "experiment_name": "Fresh Collection - Brand Defense",
    "strategy_id": "BRAND_DEFENSE",
    "week_start": "2026-03-01",
    "sales": 645.15,
    "ads_spend": 4.64,
    "total_orders": 13,
    "ads_orders": 0,
    "organic_orders": 13,
    "sessions": 264,
    "conv_rate": 0.0,
    "net_roas": 138.04,
    "organic_pct": 100.0
  },
  {
    "experiment_id": "FRESH_IN_BEIGE_LOW_COST_DISCOVERY_GIFT_GENERAL",
    "experiment_name": "Fresh - Auto Discovery",
    "strategy_id": "LOW_COST_DISCOVERY",
    "week_start": "2025-12-28",
    "sales": 1194.05,
    "ads_spend": 15.57,
    "total_orders": 23,
    "ads_orders": 0,
    "organic_orders": 23,
    "sessions": 363,
    "conv_rate": 0.0,
    "net_roas": 75.69,
    "organic_pct": 100.0
  },
  {
    "experiment_id": "FRESH_IN_BEIGE_LOW_COST_DISCOVERY_GIFT_GENERAL",
    "experiment_name": "Fresh - Auto Discovery",
    "strategy_id": "LOW_COST_DISCOVERY",
    "week_start": "2026-01-04",
    "sales": 2195.6,
    "ads_spend": 81.37,
    "total_orders": 44,
    "ads_orders": 2,
    "organic_orders": 42,
    "sessions": 907,
    "conv_rate": 0.22,
    "net_roas": 25.98,
    "organic_pct": 95.5
  },
  {
    "experiment_id": "FRESH_IN_BEIGE_LOW_COST_DISCOVERY_GIFT_GENERAL",
    "experiment_name": "Fresh - Auto Discovery",
    "strategy_id": "LOW_COST_DISCOVERY",
    "week_start": "2026-01-11",
    "sales": 1896.2,
    "ads_spend": 61.38,
    "total_orders": 33,
    "ads_orders": 2,
    "organic_orders": 31,
    "sessions": 745,
    "conv_rate": 0.27,
    "net_roas": 29.89,
    "organic_pct": 93.9
  },
  {
    "experiment_id": "FRESH_IN_BEIGE_LOW_COST_DISCOVERY_GIFT_GENERAL",
    "experiment_name": "Fresh - Auto Discovery",
    "strategy_id": "LOW_COST_DISCOVERY",
    "week_start": "2026-01-18",
    "sales": 2288.3,
    "ads_spend": 56.6,
    "total_orders": 47,
    "ads_orders": 7,
    "organic_orders": 40,
    "sessions": 960,
    "conv_rate": 0.73,
    "net_roas": 39.43,
    "organic_pct": 85.1
  },
  {
    "experiment_id": "FRESH_IN_BEIGE_LOW_COST_DISCOVERY_GIFT_GENERAL",
    "experiment_name": "Fresh - Auto Discovery",
    "strategy_id": "LOW_COST_DISCOVERY",
    "week_start": "2026-01-25",
    "sales": 1393.65,
    "ads_spend": 157.94,
    "total_orders": 28,
    "ads_orders": 7,
    "organic_orders": 21,
    "sessions": 685,
    "conv_rate": 1.02,
    "net_roas": 7.82,
    "organic_pct": 75.0
  },
  {
    "experiment_id": "FRESH_IN_BEIGE_LOW_COST_DISCOVERY_GIFT_GENERAL",
    "experiment_name": "Fresh - Auto Discovery",
    "strategy_id": "LOW_COST_DISCOVERY",
    "week_start": "2026-02-01",
    "sales": 2142.15,
    "ads_spend": 150.74,
    "total_orders": 43,
    "ads_orders": 14,
    "organic_orders": 29,
    "sessions": 698,
    "conv_rate": 2.01,
    "net_roas": 13.21,
    "organic_pct": 67.4
  },
  {
    "experiment_id": "FRESH_IN_BEIGE_LOW_COST_DISCOVERY_GIFT_GENERAL",
    "experiment_name": "Fresh - Auto Discovery",
    "strategy_id": "LOW_COST_DISCOVERY",
    "week_start": "2026-02-08",
    "sales": 2438.0,
    "ads_spend": 123.59,
    "total_orders": 49,
    "ads_orders": 10,
    "organic_orders": 39,
    "sessions": 729,
    "conv_rate": 1.37,
    "net_roas": 18.73,
    "organic_pct": 79.6
  },
  {
    "experiment_id": "FRESH_IN_BEIGE_LOW_COST_DISCOVERY_GIFT_GENERAL",
    "experiment_name": "Fresh - Auto Discovery",
    "strategy_id": "LOW_COST_DISCOVERY",
    "week_start": "2026-02-15",
    "sales": 1147.7,
    "ads_spend": 81.98,
    "total_orders": 23,
    "ads_orders": 1,
    "organic_orders": 22,
    "sessions": 468,
    "conv_rate": 0.21,
    "net_roas": 13.0,
    "organic_pct": 95.7
  },
  {
    "experiment_id": "FRESH_IN_BEIGE_LOW_COST_DISCOVERY_GIFT_GENERAL",
    "experiment_name": "Fresh - Auto Discovery",
    "strategy_id": "LOW_COST_DISCOVERY",
    "week_start": "2026-02-22",
    "sales": 898.2,
    "ads_spend": 133.31,
    "total_orders": 18,
    "ads_orders": 6,
    "organic_orders": 12,
    "sessions": 538,
    "conv_rate": 1.12,
    "net_roas": 5.74,
    "organic_pct": 66.7
  },
  {
    "experiment_id": "FRESH_IN_BEIGE_LOW_COST_DISCOVERY_GIFT_GENERAL",
    "experiment_name": "Fresh - Auto Discovery",
    "strategy_id": "LOW_COST_DISCOVERY",
    "week_start": "2026-03-01",
    "sales": 645.15,
    "ads_spend": 4.64,
    "total_orders": 13,
    "ads_orders": 0,
    "organic_orders": 13,
    "sessions": 264,
    "conv_rate": 0.0,
    "net_roas": 138.04,
    "organic_pct": 100.0
  },
  {
    "experiment_id": "FRESH_PRODUCT_DEFENSE",
    "experiment_name": "Fresh Collection - Product Defense",
    "strategy_id": "PRODUCT_DEFENSE",
    "week_start": "2026-02-08",
    "sales": 1286.75,
    "ads_spend": 1302.4,
    "total_orders": 25,
    "ads_orders": 61,
    "organic_orders": -36,
    "sessions": 1220,
    "conv_rate": 5.0,
    "net_roas": -0.01,
    "organic_pct": -144.0
  },
  {
    "experiment_id": "FRESH_PRODUCT_DEFENSE",
    "experiment_name": "Fresh Collection - Product Defense",
    "strategy_id": "PRODUCT_DEFENSE",
    "week_start": "2026-02-15",
    "sales": 2541.35,
    "ads_spend": 876.05,
    "total_orders": 52,
    "ads_orders": 74,
    "organic_orders": -22,
    "sessions": 979,
    "conv_rate": 7.56,
    "net_roas": 1.9,
    "organic_pct": -42.3
  },
  {
    "experiment_id": "FRESH_PRODUCT_DEFENSE",
    "experiment_name": "Fresh Collection - Product Defense",
    "strategy_id": "PRODUCT_DEFENSE",
    "week_start": "2026-02-22",
    "sales": 3742.5,
    "ads_spend": 1082.16,
    "total_orders": 72,
    "ads_orders": 79,
    "organic_orders": -7,
    "sessions": 1082,
    "conv_rate": 7.3,
    "net_roas": 2.46,
    "organic_pct": -9.7
  },
  {
    "experiment_id": "FRESH_PRODUCT_DEFENSE",
    "experiment_name": "Fresh Collection - Product Defense",
    "strategy_id": "PRODUCT_DEFENSE",
    "week_start": "2026-03-01",
    "sales": 3785.3,
    "ads_spend": 974.85,
    "total_orders": 73,
    "ads_orders": 81,
    "organic_orders": -8,
    "sessions": 695,
    "conv_rate": 11.65,
    "net_roas": 2.88,
    "organic_pct": -11.0
  },
  {
    "experiment_id": "LOLLIBOX_BRAND_DEFENSE_BRAND",
    "experiment_name": "Lollibox - Brand Defense",
    "strategy_id": "BRAND_DEFENSE",
    "week_start": "2026-02-08",
    "sales": 4776.32,
    "ads_spend": 1358.97,
    "total_orders": 82,
    "ads_orders": 69,
    "organic_orders": 13,
    "sessions": 3760,
    "conv_rate": 1.84,
    "net_roas": 2.51,
    "organic_pct": 15.9
  },
  {
    "experiment_id": "LOLLIBOX_BRAND_DEFENSE_BRAND",
    "experiment_name": "Lollibox - Brand Defense",
    "strategy_id": "BRAND_DEFENSE",
    "week_start": "2026-02-15",
    "sales": 3419.04,
    "ads_spend": 901.81,
    "total_orders": 63,
    "ads_orders": 42,
    "organic_orders": 21,
    "sessions": 3286,
    "conv_rate": 1.28,
    "net_roas": 2.79,
    "organic_pct": 33.3
  },
  {
    "experiment_id": "LOLLIBOX_BRAND_DEFENSE_BRAND",
    "experiment_name": "Lollibox - Brand Defense",
    "strategy_id": "BRAND_DEFENSE",
    "week_start": "2026-02-22",
    "sales": 3367.36,
    "ads_spend": 1256.84,
    "total_orders": 60,
    "ads_orders": 63,
    "organic_orders": -3,
    "sessions": 3436,
    "conv_rate": 1.83,
    "net_roas": 1.68,
    "organic_pct": -5.0
  },
  {
    "experiment_id": "LOLLIBOX_BRAND_DEFENSE_BRAND",
    "experiment_name": "Lollibox - Brand Defense",
    "strategy_id": "BRAND_DEFENSE",
    "week_start": "2026-03-01",
    "sales": 4131.68,
    "ads_spend": 2119.5,
    "total_orders": 72,
    "ads_orders": 138,
    "organic_orders": -66,
    "sessions": 2707,
    "conv_rate": 5.1,
    "net_roas": 0.95,
    "organic_pct": -91.7
  },
  {
    "experiment_id": "LOLLIBOX_HUNTER_GIFT_KIDS",
    "experiment_name": "Lollibox - Store Broad By Age",
    "strategy_id": "HUNTER",
    "week_start": "2025-12-28",
    "sales": 3261.28,
    "ads_spend": 805.07,
    "total_orders": 59,
    "ads_orders": 49,
    "organic_orders": 10,
    "sessions": 2781,
    "conv_rate": 1.76,
    "net_roas": 3.05,
    "organic_pct": 16.9
  },
  {
    "experiment_id": "LOLLIBOX_HUNTER_GIFT_KIDS",
    "experiment_name": "Lollibox - Store Broad By Age",
    "strategy_id": "HUNTER",
    "week_start": "2026-01-04",
    "sales": 8747.52,
    "ads_spend": 2710.38,
    "total_orders": 160,
    "ads_orders": 127,
    "organic_orders": 33,
    "sessions": 7884,
    "conv_rate": 1.61,
    "net_roas": 2.23,
    "organic_pct": 20.6
  },
  {
    "experiment_id": "LOLLIBOX_HUNTER_GIFT_KIDS",
    "experiment_name": "Lollibox - Store Broad By Age",
    "strategy_id": "HUNTER",
    "week_start": "2026-01-11",
    "sales": 8309.6,
    "ads_spend": 2401.61,
    "total_orders": 144,
    "ads_orders": 114,
    "organic_orders": 30,
    "sessions": 7723,
    "conv_rate": 1.48,
    "net_roas": 2.46,
    "organic_pct": 20.8
  },
  {
    "experiment_id": "LOLLIBOX_HUNTER_GIFT_KIDS",
    "experiment_name": "Lollibox - Store Broad By Age",
    "strategy_id": "HUNTER",
    "week_start": "2026-01-18",
    "sales": 8483.68,
    "ads_spend": 2129.49,
    "total_orders": 150,
    "ads_orders": 117,
    "organic_orders": 33,
    "sessions": 7766,
    "conv_rate": 1.51,
    "net_roas": 2.98,
    "organic_pct": 22.0
  },
  {
    "experiment_id": "LOLLIBOX_HUNTER_GIFT_KIDS",
    "experiment_name": "Lollibox - Store Broad By Age",
    "strategy_id": "HUNTER",
    "week_start": "2026-01-25",
    "sales": 9325.08,
    "ads_spend": 1960.13,
    "total_orders": 125,
    "ads_orders": 96,
    "organic_orders": 29,
    "sessions": 7616,
    "conv_rate": 1.26,
    "net_roas": 3.76,
    "organic_pct": 23.2
  },
  {
    "experiment_id": "LOLLIBOX_HUNTER_GIFT_KIDS",
    "experiment_name": "Lollibox - Store Broad By Age",
    "strategy_id": "HUNTER",
    "week_start": "2026-02-01",
    "sales": 8374.88,
    "ads_spend": 1817.27,
    "total_orders": 152,
    "ads_orders": 123,
    "organic_orders": 29,
    "sessions": 6864,
    "conv_rate": 1.79,
    "net_roas": 3.61,
    "organic_pct": 19.1
  },
  {
    "experiment_id": "LOLLIBOX_HUNTER_GIFT_KIDS",
    "experiment_name": "Lollibox - Store Broad By Age",
    "strategy_id": "HUNTER",
    "week_start": "2026-02-08",
    "sales": 7711.2,
    "ads_spend": 2081.22,
    "total_orders": 136,
    "ads_orders": 123,
    "organic_orders": 13,
    "sessions": 6363,
    "conv_rate": 1.93,
    "net_roas": 2.71,
    "organic_pct": 9.6
  },
  {
    "experiment_id": "LOLLIBOX_HUNTER_GIFT_KIDS",
    "experiment_name": "Lollibox - Store Broad By Age",
    "strategy_id": "HUNTER",
    "week_start": "2026-02-15",
    "sales": 5323.04,
    "ads_spend": 1543.52,
    "total_orders": 98,
    "ads_orders": 76,
    "organic_orders": 22,
    "sessions": 4744,
    "conv_rate": 1.6,
    "net_roas": 2.45,
    "organic_pct": 22.4
  },
  {
    "experiment_id": "LOLLIBOX_HUNTER_GIFT_KIDS",
    "experiment_name": "Lollibox - Store Broad By Age",
    "strategy_id": "HUNTER",
    "week_start": "2026-02-22",
    "sales": 4944.96,
    "ads_spend": 1835.06,
    "total_orders": 89,
    "ads_orders": 90,
    "organic_orders": -1,
    "sessions": 4684,
    "conv_rate": 1.92,
    "net_roas": 1.69,
    "organic_pct": -1.1
  },
  {
    "experiment_id": "LOLLIBOX_HUNTER_GIFT_KIDS",
    "experiment_name": "Lollibox - Store Broad By Age",
    "strategy_id": "HUNTER",
    "week_start": "2026-03-01",
    "sales": 6090.08,
    "ads_spend": 2083.32,
    "total_orders": 108,
    "ads_orders": 102,
    "organic_orders": 6,
    "sessions": 4411,
    "conv_rate": 2.31,
    "net_roas": 1.92,
    "organic_pct": 5.6
  },
  {
    "experiment_id": "LOLLIBOX_PRODUCT_DEFENSE",
    "experiment_name": "Lollibox - Product Defense",
    "strategy_id": "PRODUCT_DEFENSE",
    "week_start": "2026-02-08",
    "sales": 4776.32,
    "ads_spend": 1358.97,
    "total_orders": 82,
    "ads_orders": 69,
    "organic_orders": 13,
    "sessions": 3760,
    "conv_rate": 1.84,
    "net_roas": 2.51,
    "organic_pct": 15.9
  },
  {
    "experiment_id": "LOLLIBOX_PRODUCT_DEFENSE",
    "experiment_name": "Lollibox - Product Defense",
    "strategy_id": "PRODUCT_DEFENSE",
    "week_start": "2026-02-15",
    "sales": 3419.04,
    "ads_spend": 901.81,
    "total_orders": 63,
    "ads_orders": 42,
    "organic_orders": 21,
    "sessions": 3286,
    "conv_rate": 1.28,
    "net_roas": 2.79,
    "organic_pct": 33.3
  },
  {
    "experiment_id": "LOLLIBOX_PRODUCT_DEFENSE",
    "experiment_name": "Lollibox - Product Defense",
    "strategy_id": "PRODUCT_DEFENSE",
    "week_start": "2026-02-22",
    "sales": 3367.36,
    "ads_spend": 1231.99,
    "total_orders": 60,
    "ads_orders": 62,
    "organic_orders": -2,
    "sessions": 3436,
    "conv_rate": 1.8,
    "net_roas": 1.73,
    "organic_pct": -3.3
  },
  {
    "experiment_id": "LOLLIBOX_PRODUCT_DEFENSE",
    "experiment_name": "Lollibox - Product Defense",
    "strategy_id": "PRODUCT_DEFENSE",
    "week_start": "2026-03-01",
    "sales": 4131.68,
    "ads_spend": 1339.68,
    "total_orders": 72,
    "ads_orders": 68,
    "organic_orders": 4,
    "sessions": 2707,
    "conv_rate": 2.51,
    "net_roas": 2.08,
    "organic_pct": 5.6
  },
  {
    "experiment_id": "LOLLIME_BRAND_DEFENSE_BRAND",
    "experiment_name": "LolliME - Brand Defense",
    "strategy_id": "BRAND_DEFENSE",
    "week_start": "2026-02-08",
    "sales": 1616.51,
    "ads_spend": 54.79,
    "total_orders": 49,
    "ads_orders": 1,
    "organic_orders": 48,
    "sessions": 928,
    "conv_rate": 0.11,
    "net_roas": 28.5,
    "organic_pct": 98.0
  },
  {
    "experiment_id": "LOLLIME_BRAND_DEFENSE_BRAND",
    "experiment_name": "LolliME - Brand Defense",
    "strategy_id": "BRAND_DEFENSE",
    "week_start": "2026-02-15",
    "sales": 2111.36,
    "ads_spend": 53.2,
    "total_orders": 64,
    "ads_orders": 3,
    "organic_orders": 61,
    "sessions": 992,
    "conv_rate": 0.3,
    "net_roas": 38.69,
    "organic_pct": 95.3
  },
  {
    "experiment_id": "LOLLIME_BRAND_DEFENSE_BRAND",
    "experiment_name": "LolliME - Brand Defense",
    "strategy_id": "BRAND_DEFENSE",
    "week_start": "2026-02-22",
    "sales": 2672.19,
    "ads_spend": 76.4,
    "total_orders": 81,
    "ads_orders": 7,
    "organic_orders": 74,
    "sessions": 968,
    "conv_rate": 0.72,
    "net_roas": 33.98,
    "organic_pct": 91.4
  },
  {
    "experiment_id": "LOLLIME_BRAND_DEFENSE_BRAND",
    "experiment_name": "LolliME - Brand Defense",
    "strategy_id": "BRAND_DEFENSE",
    "week_start": "2026-03-01",
    "sales": 2639.2,
    "ads_spend": 897.16,
    "total_orders": 80,
    "ads_orders": 88,
    "organic_orders": -8,
    "sessions": 786,
    "conv_rate": 11.2,
    "net_roas": 1.94,
    "organic_pct": -10.0
  },
  {
    "experiment_id": "LOLLIME_PRODUCT_DEFENSE",
    "experiment_name": "LolliME - Product Defense",
    "strategy_id": "PRODUCT_DEFENSE",
    "week_start": "2026-02-08",
    "sales": 2375.28,
    "ads_spend": 327.3,
    "total_orders": 72,
    "ads_orders": 30,
    "organic_orders": 42,
    "sessions": 1277,
    "conv_rate": 2.35,
    "net_roas": 6.26,
    "organic_pct": 58.3
  },
  {
    "experiment_id": "LOLLIME_PRODUCT_DEFENSE",
    "experiment_name": "LolliME - Product Defense",
    "strategy_id": "PRODUCT_DEFENSE",
    "week_start": "2026-02-15",
    "sales": 2243.32,
    "ads_spend": 289.03,
    "total_orders": 68,
    "ads_orders": 26,
    "organic_orders": 42,
    "sessions": 1431,
    "conv_rate": 1.82,
    "net_roas": 6.76,
    "organic_pct": 61.8
  },
  {
    "experiment_id": "LOLLIME_PRODUCT_DEFENSE",
    "experiment_name": "LolliME - Product Defense",
    "strategy_id": "PRODUCT_DEFENSE",
    "week_start": "2026-02-22",
    "sales": 3101.06,
    "ads_spend": 771.94,
    "total_orders": 92,
    "ads_orders": 90,
    "organic_orders": 2,
    "sessions": 1819,
    "conv_rate": 4.95,
    "net_roas": 3.02,
    "organic_pct": 2.2
  },
  {
    "experiment_id": "LOLLIME_PRODUCT_DEFENSE",
    "experiment_name": "LolliME - Product Defense",
    "strategy_id": "PRODUCT_DEFENSE",
    "week_start": "2026-03-01",
    "sales": 2606.21,
    "ads_spend": 893.85,
    "total_orders": 78,
    "ads_orders": 78,
    "organic_orders": 0,
    "sessions": 1294,
    "conv_rate": 6.03,
    "net_roas": 1.92,
    "organic_pct": 0.0
  },
  {
    "experiment_id": "MINT_LOLLIME_CATEGORY_CONQUEST_GIFT_GENERAL",
    "experiment_name": "Mint LolliME - Competitor Conquest",
    "strategy_id": "CATEGORY_CONQUEST",
    "week_start": "2025-12-28",
    "sales": 1748.02,
    "ads_spend": 688.71,
    "total_orders": 53,
    "ads_orders": 45,
    "organic_orders": 8,
    "sessions": 1199,
    "conv_rate": 3.75,
    "net_roas": 1.54,
    "organic_pct": 15.1
  },
  {
    "experiment_id": "MINT_LOLLIME_CATEGORY_CONQUEST_GIFT_GENERAL",
    "experiment_name": "Mint LolliME - Competitor Conquest",
    "strategy_id": "CATEGORY_CONQUEST",
    "week_start": "2026-01-04",
    "sales": 5872.22,
    "ads_spend": 1953.83,
    "total_orders": 179,
    "ads_orders": 131,
    "organic_orders": 48,
    "sessions": 3480,
    "conv_rate": 3.76,
    "net_roas": 2.01,
    "organic_pct": 26.8
  },
  {
    "experiment_id": "MINT_LOLLIME_CATEGORY_CONQUEST_GIFT_GENERAL",
    "experiment_name": "Mint LolliME - Competitor Conquest",
    "strategy_id": "CATEGORY_CONQUEST",
    "week_start": "2026-01-11",
    "sales": 6400.06,
    "ads_spend": 2084.21,
    "total_orders": 186,
    "ads_orders": 144,
    "organic_orders": 42,
    "sessions": 3596,
    "conv_rate": 4.0,
    "net_roas": 2.07,
    "organic_pct": 22.6
  },
  {
    "experiment_id": "MINT_LOLLIME_CATEGORY_CONQUEST_GIFT_GENERAL",
    "experiment_name": "Mint LolliME - Competitor Conquest",
    "strategy_id": "CATEGORY_CONQUEST",
    "week_start": "2026-01-18",
    "sales": 5938.2,
    "ads_spend": 2010.39,
    "total_orders": 176,
    "ads_orders": 110,
    "organic_orders": 66,
    "sessions": 3974,
    "conv_rate": 2.77,
    "net_roas": 1.95,
    "organic_pct": 37.5
  },
  {
    "experiment_id": "MINT_LOLLIME_CATEGORY_CONQUEST_GIFT_GENERAL",
    "experiment_name": "Mint LolliME - Competitor Conquest",
    "strategy_id": "CATEGORY_CONQUEST",
    "week_start": "2026-01-25",
    "sales": 4552.62,
    "ads_spend": 1430.13,
    "total_orders": 139,
    "ads_orders": 92,
    "organic_orders": 47,
    "sessions": 3393,
    "conv_rate": 2.71,
    "net_roas": 2.18,
    "organic_pct": 33.8
  },
  {
    "experiment_id": "MINT_LOLLIME_CATEGORY_CONQUEST_GIFT_GENERAL",
    "experiment_name": "Mint LolliME - Competitor Conquest",
    "strategy_id": "CATEGORY_CONQUEST",
    "week_start": "2026-02-01",
    "sales": 4882.52,
    "ads_spend": 1039.95,
    "total_orders": 148,
    "ads_orders": 92,
    "organic_orders": 56,
    "sessions": 3116,
    "conv_rate": 2.95,
    "net_roas": 3.69,
    "organic_pct": 37.8
  },
  {
    "experiment_id": "MINT_LOLLIME_CATEGORY_CONQUEST_GIFT_GENERAL",
    "experiment_name": "Mint LolliME - Competitor Conquest",
    "strategy_id": "CATEGORY_CONQUEST",
    "week_start": "2026-02-08",
    "sales": 4519.63,
    "ads_spend": 869.73,
    "total_orders": 137,
    "ads_orders": 82,
    "organic_orders": 55,
    "sessions": 2679,
    "conv_rate": 3.06,
    "net_roas": 4.2,
    "organic_pct": 40.1
  },
  {
    "experiment_id": "MINT_LOLLIME_CATEGORY_CONQUEST_GIFT_GENERAL",
    "experiment_name": "Mint LolliME - Competitor Conquest",
    "strategy_id": "CATEGORY_CONQUEST",
    "week_start": "2026-02-15",
    "sales": 2936.11,
    "ads_spend": 672.03,
    "total_orders": 89,
    "ads_orders": 67,
    "organic_orders": 22,
    "sessions": 1367,
    "conv_rate": 4.9,
    "net_roas": 3.37,
    "organic_pct": 24.7
  },
  {
    "experiment_id": "MINT_LOLLIME_EXACT_BOOST_GIFT_GENERAL",
    "experiment_name": "Mint LolliME - Exact T2",
    "strategy_id": "EXACT_BOOST",
    "week_start": "2025-12-28",
    "sales": 1748.02,
    "ads_spend": 320.22,
    "total_orders": 53,
    "ads_orders": 23,
    "organic_orders": 30,
    "sessions": 1199,
    "conv_rate": 1.92,
    "net_roas": 4.46,
    "organic_pct": 56.6
  },
  {
    "experiment_id": "MINT_LOLLIME_EXACT_BOOST_GIFT_GENERAL",
    "experiment_name": "Mint LolliME - Exact T2",
    "strategy_id": "EXACT_BOOST",
    "week_start": "2026-01-04",
    "sales": 5872.22,
    "ads_spend": 805.22,
    "total_orders": 179,
    "ads_orders": 48,
    "organic_orders": 131,
    "sessions": 3480,
    "conv_rate": 1.38,
    "net_roas": 6.29,
    "organic_pct": 73.2
  },
  {
    "experiment_id": "MINT_LOLLIME_EXACT_BOOST_GIFT_GENERAL",
    "experiment_name": "Mint LolliME - Exact T2",
    "strategy_id": "EXACT_BOOST",
    "week_start": "2026-01-11",
    "sales": 6400.06,
    "ads_spend": 1002.53,
    "total_orders": 186,
    "ads_orders": 76,
    "organic_orders": 110,
    "sessions": 3596,
    "conv_rate": 2.11,
    "net_roas": 5.38,
    "organic_pct": 59.1
  },
  {
    "experiment_id": "MINT_LOLLIME_EXACT_BOOST_GIFT_GENERAL",
    "experiment_name": "Mint LolliME - Exact T2",
    "strategy_id": "EXACT_BOOST",
    "week_start": "2026-01-18",
    "sales": 5938.2,
    "ads_spend": 1100.63,
    "total_orders": 176,
    "ads_orders": 44,
    "organic_orders": 132,
    "sessions": 3974,
    "conv_rate": 1.11,
    "net_roas": 4.4,
    "organic_pct": 75.0
  },
  {
    "experiment_id": "MINT_LOLLIME_EXACT_BOOST_GIFT_GENERAL",
    "experiment_name": "Mint LolliME - Exact T2",
    "strategy_id": "EXACT_BOOST",
    "week_start": "2026-01-25",
    "sales": 4552.62,
    "ads_spend": 826.57,
    "total_orders": 139,
    "ads_orders": 46,
    "organic_orders": 93,
    "sessions": 3393,
    "conv_rate": 1.36,
    "net_roas": 4.51,
    "organic_pct": 66.9
  },
  {
    "experiment_id": "MINT_LOLLIME_EXACT_BOOST_GIFT_GENERAL",
    "experiment_name": "Mint LolliME - Exact T2",
    "strategy_id": "EXACT_BOOST",
    "week_start": "2026-02-01",
    "sales": 4882.52,
    "ads_spend": 660.41,
    "total_orders": 148,
    "ads_orders": 64,
    "organic_orders": 84,
    "sessions": 3116,
    "conv_rate": 2.05,
    "net_roas": 6.39,
    "organic_pct": 56.8
  },
  {
    "experiment_id": "MINT_LOLLIME_EXACT_BOOST_GIFT_GENERAL",
    "experiment_name": "Mint LolliME - Exact T2",
    "strategy_id": "EXACT_BOOST",
    "week_start": "2026-02-08",
    "sales": 4519.63,
    "ads_spend": 492.23,
    "total_orders": 137,
    "ads_orders": 34,
    "organic_orders": 103,
    "sessions": 2679,
    "conv_rate": 1.27,
    "net_roas": 8.18,
    "organic_pct": 75.2
  },
  {
    "experiment_id": "MINT_LOLLIME_EXACT_BOOST_GIFT_GENERAL",
    "experiment_name": "Mint LolliME - Exact T2",
    "strategy_id": "EXACT_BOOST",
    "week_start": "2026-02-15",
    "sales": 2936.11,
    "ads_spend": 271.67,
    "total_orders": 89,
    "ads_orders": 19,
    "organic_orders": 70,
    "sessions": 1367,
    "conv_rate": 1.39,
    "net_roas": 9.81,
    "organic_pct": 78.7
  },
  {
    "experiment_id": "MINT_LOLLIME_EXACT_BOOST_GIFT_GENERAL_HOLIDAY_2025",
    "experiment_name": "Mint LolliME - Exact T2 (Holiday 2025)",
    "strategy_id": "EXACT_BOOST",
    "week_start": "2025-12-14",
    "sales": 65503.9,
    "ads_spend": 6180.26,
    "total_orders": 1958,
    "ads_orders": 677,
    "organic_orders": 1281,
    "sessions": 17781,
    "conv_rate": 3.81,
    "net_roas": 9.6,
    "organic_pct": 65.4
  },
  {
    "experiment_id": "MINT_LOLLIME_EXACT_BOOST_GIFT_GENERAL_HOLIDAY_2025",
    "experiment_name": "Mint LolliME - Exact T2 (Holiday 2025)",
    "strategy_id": "EXACT_BOOST",
    "week_start": "2025-12-21",
    "sales": 13225.8,
    "ads_spend": 2017.14,
    "total_orders": 394,
    "ads_orders": 146,
    "organic_orders": 248,
    "sessions": 7369,
    "conv_rate": 1.98,
    "net_roas": 5.56,
    "organic_pct": 62.9
  },
  {
    "experiment_id": "MINT_LOLLIME_EXACT_BOOST_GIFT_GENERAL_HOLIDAY_2025",
    "experiment_name": "Mint LolliME - Exact T2 (Holiday 2025)",
    "strategy_id": "EXACT_BOOST",
    "week_start": "2025-12-28",
    "sales": 3257.1,
    "ads_spend": 393.88,
    "total_orders": 93,
    "ads_orders": 44,
    "organic_orders": 49,
    "sessions": 1510,
    "conv_rate": 2.91,
    "net_roas": 7.27,
    "organic_pct": 52.7
  },
  {
    "experiment_id": "MINT_LOLLIME_HUNTER_GIFT_GENERAL",
    "experiment_name": "Mint LolliME - Store Broad Discovery",
    "strategy_id": "HUNTER",
    "week_start": "2025-12-28",
    "sales": 725.6,
    "ads_spend": 320.22,
    "total_orders": 22,
    "ads_orders": 23,
    "organic_orders": -1,
    "sessions": 578,
    "conv_rate": 3.98,
    "net_roas": 1.27,
    "organic_pct": -4.5
  },
  {
    "experiment_id": "MINT_LOLLIME_HUNTER_GIFT_GENERAL",
    "experiment_name": "Mint LolliME - Store Broad Discovery",
    "strategy_id": "HUNTER",
    "week_start": "2026-01-04",
    "sales": 2474.25,
    "ads_spend": 805.22,
    "total_orders": 76,
    "ads_orders": 48,
    "organic_orders": 28,
    "sessions": 1482,
    "conv_rate": 3.24,
    "net_roas": 2.07,
    "organic_pct": 36.8
  },
  {
    "experiment_id": "MINT_LOLLIME_HUNTER_GIFT_GENERAL",
    "experiment_name": "Mint LolliME - Store Broad Discovery",
    "strategy_id": "HUNTER",
    "week_start": "2026-01-11",
    "sales": 2969.1,
    "ads_spend": 1001.83,
    "total_orders": 90,
    "ads_orders": 76,
    "organic_orders": 14,
    "sessions": 1778,
    "conv_rate": 4.27,
    "net_roas": 1.96,
    "organic_pct": 15.6
  },
  {
    "experiment_id": "MINT_LOLLIME_HUNTER_GIFT_GENERAL",
    "experiment_name": "Mint LolliME - Store Broad Discovery",
    "strategy_id": "HUNTER",
    "week_start": "2026-01-18",
    "sales": 2738.17,
    "ads_spend": 1099.23,
    "total_orders": 80,
    "ads_orders": 44,
    "organic_orders": 36,
    "sessions": 1950,
    "conv_rate": 2.26,
    "net_roas": 1.49,
    "organic_pct": 45.0
  },
  {
    "experiment_id": "MINT_LOLLIME_HUNTER_GIFT_GENERAL",
    "experiment_name": "Mint LolliME - Store Broad Discovery",
    "strategy_id": "HUNTER",
    "week_start": "2026-01-25",
    "sales": 2474.25,
    "ads_spend": 817.19,
    "total_orders": 75,
    "ads_orders": 45,
    "organic_orders": 30,
    "sessions": 1815,
    "conv_rate": 2.48,
    "net_roas": 2.03,
    "organic_pct": 40.0
  },
  {
    "experiment_id": "MINT_LOLLIME_HUNTER_GIFT_GENERAL",
    "experiment_name": "Mint LolliME - Store Broad Discovery",
    "strategy_id": "HUNTER",
    "week_start": "2026-02-01",
    "sales": 2210.33,
    "ads_spend": 594.22,
    "total_orders": 67,
    "ads_orders": 50,
    "organic_orders": 17,
    "sessions": 1709,
    "conv_rate": 2.93,
    "net_roas": 2.72,
    "organic_pct": 25.4
  },
  {
    "experiment_id": "MINT_LOLLIME_HUNTER_GIFT_GENERAL",
    "experiment_name": "Mint LolliME - Store Broad Discovery",
    "strategy_id": "HUNTER",
    "week_start": "2026-02-08",
    "sales": 2639.2,
    "ads_spend": 431.32,
    "total_orders": 80,
    "ads_orders": 33,
    "organic_orders": 47,
    "sessions": 1560,
    "conv_rate": 2.12,
    "net_roas": 5.12,
    "organic_pct": 58.8
  },
  {
    "experiment_id": "MINT_LOLLIME_HUNTER_GIFT_GENERAL",
    "experiment_name": "Mint LolliME - Store Broad Discovery",
    "strategy_id": "HUNTER",
    "week_start": "2026-02-15",
    "sales": 1484.55,
    "ads_spend": 218.47,
    "total_orders": 45,
    "ads_orders": 16,
    "organic_orders": 29,
    "sessions": 796,
    "conv_rate": 2.01,
    "net_roas": 5.8,
    "organic_pct": 64.4
  },
  {
    "experiment_id": "MINT_LOLLIME_LOW_COST_DISCOVERY_GIFT_GENERAL",
    "experiment_name": "Mint LolliME - Auto Discovery",
    "strategy_id": "LOW_COST_DISCOVERY",
    "week_start": "2025-12-28",
    "sales": 725.6,
    "ads_spend": 687.56,
    "total_orders": 22,
    "ads_orders": 45,
    "organic_orders": -23,
    "sessions": 578,
    "conv_rate": 7.79,
    "net_roas": 0.06,
    "organic_pct": -104.5
  },
  {
    "experiment_id": "MINT_LOLLIME_LOW_COST_DISCOVERY_GIFT_GENERAL",
    "experiment_name": "Mint LolliME - Auto Discovery",
    "strategy_id": "LOW_COST_DISCOVERY",
    "week_start": "2026-01-04",
    "sales": 2474.25,
    "ads_spend": 1953.83,
    "total_orders": 76,
    "ads_orders": 131,
    "organic_orders": -55,
    "sessions": 1482,
    "conv_rate": 8.84,
    "net_roas": 0.27,
    "organic_pct": -72.4
  },
  {
    "experiment_id": "MINT_LOLLIME_LOW_COST_DISCOVERY_GIFT_GENERAL",
    "experiment_name": "Mint LolliME - Auto Discovery",
    "strategy_id": "LOW_COST_DISCOVERY",
    "week_start": "2026-01-11",
    "sales": 2969.1,
    "ads_spend": 2083.51,
    "total_orders": 90,
    "ads_orders": 144,
    "organic_orders": -54,
    "sessions": 1778,
    "conv_rate": 8.1,
    "net_roas": 0.43,
    "organic_pct": -60.0
  },
  {
    "experiment_id": "MINT_LOLLIME_LOW_COST_DISCOVERY_GIFT_GENERAL",
    "experiment_name": "Mint LolliME - Auto Discovery",
    "strategy_id": "LOW_COST_DISCOVERY",
    "week_start": "2026-01-18",
    "sales": 2738.17,
    "ads_spend": 2008.99,
    "total_orders": 80,
    "ads_orders": 110,
    "organic_orders": -30,
    "sessions": 1950,
    "conv_rate": 5.64,
    "net_roas": 0.36,
    "organic_pct": -37.5
  },
  {
    "experiment_id": "MINT_LOLLIME_LOW_COST_DISCOVERY_GIFT_GENERAL",
    "experiment_name": "Mint LolliME - Auto Discovery",
    "strategy_id": "LOW_COST_DISCOVERY",
    "week_start": "2026-01-25",
    "sales": 2474.25,
    "ads_spend": 1420.75,
    "total_orders": 75,
    "ads_orders": 91,
    "organic_orders": -16,
    "sessions": 1815,
    "conv_rate": 5.01,
    "net_roas": 0.74,
    "organic_pct": -21.3
  },
  {
    "experiment_id": "MINT_LOLLIME_LOW_COST_DISCOVERY_GIFT_GENERAL",
    "experiment_name": "Mint LolliME - Auto Discovery",
    "strategy_id": "LOW_COST_DISCOVERY",
    "week_start": "2026-02-01",
    "sales": 2210.33,
    "ads_spend": 970.51,
    "total_orders": 67,
    "ads_orders": 81,
    "organic_orders": -14,
    "sessions": 1709,
    "conv_rate": 4.74,
    "net_roas": 1.28,
    "organic_pct": -20.9
  },
  {
    "experiment_id": "MINT_LOLLIME_LOW_COST_DISCOVERY_GIFT_GENERAL",
    "experiment_name": "Mint LolliME - Auto Discovery",
    "strategy_id": "LOW_COST_DISCOVERY",
    "week_start": "2026-02-08",
    "sales": 2639.2,
    "ads_spend": 783.33,
    "total_orders": 80,
    "ads_orders": 81,
    "organic_orders": -1,
    "sessions": 1560,
    "conv_rate": 5.19,
    "net_roas": 2.37,
    "organic_pct": -1.3
  },
  {
    "experiment_id": "MINT_LOLLIME_LOW_COST_DISCOVERY_GIFT_GENERAL",
    "experiment_name": "Mint LolliME - Auto Discovery",
    "strategy_id": "LOW_COST_DISCOVERY",
    "week_start": "2026-02-15",
    "sales": 2243.32,
    "ads_spend": 738.83,
    "total_orders": 68,
    "ads_orders": 82,
    "organic_orders": -14,
    "sessions": 1431,
    "conv_rate": 5.73,
    "net_roas": 2.04,
    "organic_pct": -20.6
  },
  {
    "experiment_id": "MINT_LOLLIME_LOW_COST_DISCOVERY_GIFT_GENERAL",
    "experiment_name": "Mint LolliME - Auto Discovery",
    "strategy_id": "LOW_COST_DISCOVERY",
    "week_start": "2026-02-22",
    "sales": 3101.06,
    "ads_spend": 897.11,
    "total_orders": 92,
    "ads_orders": 99,
    "organic_orders": -7,
    "sessions": 1819,
    "conv_rate": 5.44,
    "net_roas": 2.46,
    "organic_pct": -7.6
  },
  {
    "experiment_id": "MINT_LOLLIME_LOW_COST_DISCOVERY_GIFT_GENERAL",
    "experiment_name": "Mint LolliME - Auto Discovery",
    "strategy_id": "LOW_COST_DISCOVERY",
    "week_start": "2026-03-01",
    "sales": 2606.21,
    "ads_spend": 924.12,
    "total_orders": 78,
    "ads_orders": 83,
    "organic_orders": -5,
    "sessions": 1294,
    "conv_rate": 6.41,
    "net_roas": 1.82,
    "organic_pct": -6.4
  },
  {
    "experiment_id": "PINK_LOLLIBOX_HUNTER_GIFT_GENERAL",
    "experiment_name": "Pink Lollibox - Store Broad Discovery",
    "strategy_id": "HUNTER",
    "week_start": "2025-12-28",
    "sales": 269.28,
    "ads_spend": 201.39,
    "total_orders": 5,
    "ads_orders": 16,
    "organic_orders": -11,
    "sessions": 182,
    "conv_rate": 8.79,
    "net_roas": 0.34,
    "organic_pct": -220.0
  },
  {
    "experiment_id": "PINK_LOLLIBOX_HUNTER_GIFT_GENERAL",
    "experiment_name": "Pink Lollibox - Store Broad Discovery",
    "strategy_id": "HUNTER",
    "week_start": "2026-01-04",
    "sales": 108.8,
    "ads_spend": 599.49,
    "total_orders": 2,
    "ads_orders": 31,
    "organic_orders": -29,
    "sessions": 155,
    "conv_rate": 20.0,
    "net_roas": -0.82,
    "organic_pct": -1450.0
  },
  {
    "experiment_id": "PINK_LOLLIBOX_HUNTER_GIFT_GENERAL",
    "experiment_name": "Pink Lollibox - Store Broad Discovery",
    "strategy_id": "HUNTER",
    "week_start": "2026-01-11",
    "sales": 272.0,
    "ads_spend": 411.58,
    "total_orders": 5,
    "ads_orders": 23,
    "organic_orders": -18,
    "sessions": 431,
    "conv_rate": 5.34,
    "net_roas": -0.34,
    "organic_pct": -360.0
  },
  {
    "experiment_id": "PINK_LOLLIBOX_HUNTER_GIFT_GENERAL",
    "experiment_name": "Pink Lollibox - Store Broad Discovery",
    "strategy_id": "HUNTER",
    "week_start": "2026-01-18",
    "sales": 54.4,
    "ads_spend": 298.5,
    "total_orders": 1,
    "ads_orders": 16,
    "organic_orders": -15,
    "sessions": 253,
    "conv_rate": 6.32,
    "net_roas": -0.82,
    "organic_pct": -1500.0
  },
  {
    "experiment_id": "PINK_LOLLIBOX_HUNTER_GIFT_GENERAL",
    "experiment_name": "Pink Lollibox - Store Broad Discovery",
    "strategy_id": "HUNTER",
    "week_start": "2026-01-25",
    "sales": 134.2,
    "ads_spend": 410.71,
    "total_orders": 3,
    "ads_orders": 18,
    "organic_orders": -15,
    "sessions": 53,
    "conv_rate": 33.96,
    "net_roas": -0.67,
    "organic_pct": -500.0
  },
  {
    "experiment_id": "PINK_LOLLIBOX_HUNTER_GIFT_GENERAL",
    "experiment_name": "Pink Lollibox - Store Broad Discovery",
    "strategy_id": "HUNTER",
    "week_start": "2026-02-01",
    "sales": 108.8,
    "ads_spend": 199.47,
    "total_orders": 2,
    "ads_orders": 12,
    "organic_orders": -10,
    "sessions": 115,
    "conv_rate": 10.43,
    "net_roas": -0.45,
    "organic_pct": -500.0
  },
  {
    "experiment_id": "PINK_LOLLIBOX_HUNTER_GIFT_GENERAL",
    "experiment_name": "Pink Lollibox - Store Broad Discovery",
    "strategy_id": "HUNTER",
    "week_start": "2026-02-08",
    "sales": 217.6,
    "ads_spend": 104.93,
    "total_orders": 4,
    "ads_orders": 9,
    "organic_orders": -5,
    "sessions": 131,
    "conv_rate": 6.87,
    "net_roas": 1.07,
    "organic_pct": -125.0
  },
  {
    "experiment_id": "PINK_LOLLIBOX_HUNTER_GIFT_GENERAL",
    "experiment_name": "Pink Lollibox - Store Broad Discovery",
    "strategy_id": "HUNTER",
    "week_start": "2026-02-15",
    "sales": 54.4,
    "ads_spend": 218.85,
    "total_orders": 1,
    "ads_orders": 10,
    "organic_orders": -9,
    "sessions": 109,
    "conv_rate": 9.17,
    "net_roas": -0.75,
    "organic_pct": -900.0
  },
  {
    "experiment_id": "PINK_LOLLIBOX_HUNTER_GIFT_GENERAL",
    "experiment_name": "Pink Lollibox - Store Broad Discovery",
    "strategy_id": "HUNTER",
    "week_start": "2026-02-22",
    "sales": 54.4,
    "ads_spend": 304.26,
    "total_orders": 1,
    "ads_orders": 8,
    "organic_orders": -7,
    "sessions": 0,
    "conv_rate": null,
    "net_roas": -0.82,
    "organic_pct": -700.0
  },
  {
    "experiment_id": "PINK_LOLLIBOX_HUNTER_GIFT_GENERAL",
    "experiment_name": "Pink Lollibox - Store Broad Discovery",
    "strategy_id": "HUNTER",
    "week_start": "2026-03-01",
    "sales": 870.4,
    "ads_spend": 360.23,
    "total_orders": 16,
    "ads_orders": 17,
    "organic_orders": -1,
    "sessions": 699,
    "conv_rate": 2.43,
    "net_roas": 1.42,
    "organic_pct": -6.3
  },
  {
    "experiment_id": "TRUTH_OR_DARE_CATEGORY_CONQUEST_GIFT_GENERAL",
    "experiment_name": "Truth Or Dare - Competitor Conquest",
    "strategy_id": "CATEGORY_CONQUEST",
    "week_start": "2025-12-28",
    "sales": 538.2,
    "ads_spend": 162.77,
    "total_orders": 18,
    "ads_orders": 13,
    "organic_orders": 5,
    "sessions": 527,
    "conv_rate": 2.47,
    "net_roas": 2.31,
    "organic_pct": 27.8
  },
  {
    "experiment_id": "TRUTH_OR_DARE_CATEGORY_CONQUEST_GIFT_GENERAL",
    "experiment_name": "Truth Or Dare - Competitor Conquest",
    "strategy_id": "CATEGORY_CONQUEST",
    "week_start": "2026-01-04",
    "sales": 2003.3,
    "ads_spend": 586.93,
    "total_orders": 67,
    "ads_orders": 44,
    "organic_orders": 23,
    "sessions": 1568,
    "conv_rate": 2.81,
    "net_roas": 2.41,
    "organic_pct": 34.3
  },
  {
    "experiment_id": "TRUTH_OR_DARE_CATEGORY_CONQUEST_GIFT_GENERAL",
    "experiment_name": "Truth Or Dare - Competitor Conquest",
    "strategy_id": "CATEGORY_CONQUEST",
    "week_start": "2026-01-11",
    "sales": 1704.3,
    "ads_spend": 276.57,
    "total_orders": 56,
    "ads_orders": 21,
    "organic_orders": 35,
    "sessions": 1275,
    "conv_rate": 1.65,
    "net_roas": 5.16,
    "organic_pct": 62.5
  },
  {
    "experiment_id": "TRUTH_OR_DARE_CATEGORY_CONQUEST_GIFT_GENERAL",
    "experiment_name": "Truth Or Dare - Competitor Conquest",
    "strategy_id": "CATEGORY_CONQUEST",
    "week_start": "2026-01-18",
    "sales": 1704.3,
    "ads_spend": 281.85,
    "total_orders": 57,
    "ads_orders": 26,
    "organic_orders": 31,
    "sessions": 1212,
    "conv_rate": 2.15,
    "net_roas": 5.05,
    "organic_pct": 54.4
  },
  {
    "experiment_id": "TRUTH_OR_DARE_CATEGORY_CONQUEST_GIFT_GENERAL",
    "experiment_name": "Truth Or Dare - Competitor Conquest",
    "strategy_id": "CATEGORY_CONQUEST",
    "week_start": "2026-01-25",
    "sales": 1405.3,
    "ads_spend": 236.19,
    "total_orders": 47,
    "ads_orders": 25,
    "organic_orders": 22,
    "sessions": 1083,
    "conv_rate": 2.31,
    "net_roas": 4.95,
    "organic_pct": 46.8
  },
  {
    "experiment_id": "TRUTH_OR_DARE_CATEGORY_CONQUEST_GIFT_GENERAL",
    "experiment_name": "Truth Or Dare - Competitor Conquest",
    "strategy_id": "CATEGORY_CONQUEST",
    "week_start": "2026-02-01",
    "sales": 1584.7,
    "ads_spend": 222.54,
    "total_orders": 52,
    "ads_orders": 32,
    "organic_orders": 20,
    "sessions": 960,
    "conv_rate": 3.33,
    "net_roas": 6.12,
    "organic_pct": 38.5
  },
  {
    "experiment_id": "TRUTH_OR_DARE_CATEGORY_CONQUEST_GIFT_GENERAL",
    "experiment_name": "Truth Or Dare - Competitor Conquest",
    "strategy_id": "CATEGORY_CONQUEST",
    "week_start": "2026-02-08",
    "sales": 1644.5,
    "ads_spend": 218.99,
    "total_orders": 55,
    "ads_orders": 24,
    "organic_orders": 31,
    "sessions": 867,
    "conv_rate": 2.77,
    "net_roas": 6.51,
    "organic_pct": 56.4
  },
  {
    "experiment_id": "TRUTH_OR_DARE_CATEGORY_CONQUEST_GIFT_GENERAL",
    "experiment_name": "Truth Or Dare - Competitor Conquest",
    "strategy_id": "CATEGORY_CONQUEST",
    "week_start": "2026-02-15",
    "sales": 837.2,
    "ads_spend": 141.43,
    "total_orders": 28,
    "ads_orders": 18,
    "organic_orders": 10,
    "sessions": 542,
    "conv_rate": 3.32,
    "net_roas": 4.92,
    "organic_pct": 35.7
  },
  {
    "experiment_id": "TRUTH_OR_DARE_CATEGORY_CONQUEST_GIFT_GENERAL_HOLIDAY_2025",
    "experiment_name": "Truth Or Dare - Competitor Conquest (Holiday 2025)",
    "strategy_id": "CATEGORY_CONQUEST",
    "week_start": "2025-12-14",
    "sales": 5262.4,
    "ads_spend": 266.64,
    "total_orders": 172,
    "ads_orders": 20,
    "organic_orders": 152,
    "sessions": 2679,
    "conv_rate": 0.75,
    "net_roas": 18.74,
    "organic_pct": 88.4
  },
  {
    "experiment_id": "TRUTH_OR_DARE_CATEGORY_CONQUEST_GIFT_GENERAL_HOLIDAY_2025",
    "experiment_name": "Truth Or Dare - Competitor Conquest (Holiday 2025)",
    "strategy_id": "CATEGORY_CONQUEST",
    "week_start": "2025-12-21",
    "sales": 2093.0,
    "ads_spend": 322.16,
    "total_orders": 69,
    "ads_orders": 27,
    "organic_orders": 42,
    "sessions": 1362,
    "conv_rate": 1.98,
    "net_roas": 5.5,
    "organic_pct": 60.9
  },
  {
    "experiment_id": "TRUTH_OR_DARE_CATEGORY_CONQUEST_GIFT_GENERAL_HOLIDAY_2025",
    "experiment_name": "Truth Or Dare - Competitor Conquest (Holiday 2025)",
    "strategy_id": "CATEGORY_CONQUEST",
    "week_start": "2025-12-28",
    "sales": 657.8,
    "ads_spend": 190.71,
    "total_orders": 22,
    "ads_orders": 9,
    "organic_orders": 13,
    "sessions": 590,
    "conv_rate": 1.53,
    "net_roas": 2.45,
    "organic_pct": 59.1
  },
  {
    "experiment_id": "TRUTH_OR_DARE_EXACT_BOOST_ACTIVITY",
    "experiment_name": "Truth Or Dare - Exact Games",
    "strategy_id": "EXACT_BOOST",
    "week_start": "2025-12-28",
    "sales": 538.2,
    "ads_spend": 162.77,
    "total_orders": 18,
    "ads_orders": 13,
    "organic_orders": 5,
    "sessions": 527,
    "conv_rate": 2.47,
    "net_roas": 2.31,
    "organic_pct": 27.8
  },
  {
    "experiment_id": "TRUTH_OR_DARE_EXACT_BOOST_ACTIVITY",
    "experiment_name": "Truth Or Dare - Exact Games",
    "strategy_id": "EXACT_BOOST",
    "week_start": "2026-01-04",
    "sales": 2003.3,
    "ads_spend": 586.93,
    "total_orders": 67,
    "ads_orders": 44,
    "organic_orders": 23,
    "sessions": 1568,
    "conv_rate": 2.81,
    "net_roas": 2.41,
    "organic_pct": 34.3
  },
  {
    "experiment_id": "TRUTH_OR_DARE_EXACT_BOOST_ACTIVITY",
    "experiment_name": "Truth Or Dare - Exact Games",
    "strategy_id": "EXACT_BOOST",
    "week_start": "2026-01-11",
    "sales": 1704.3,
    "ads_spend": 276.57,
    "total_orders": 56,
    "ads_orders": 21,
    "organic_orders": 35,
    "sessions": 1275,
    "conv_rate": 1.65,
    "net_roas": 5.16,
    "organic_pct": 62.5
  },
  {
    "experiment_id": "TRUTH_OR_DARE_EXACT_BOOST_ACTIVITY",
    "experiment_name": "Truth Or Dare - Exact Games",
    "strategy_id": "EXACT_BOOST",
    "week_start": "2026-01-18",
    "sales": 1704.3,
    "ads_spend": 281.85,
    "total_orders": 57,
    "ads_orders": 26,
    "organic_orders": 31,
    "sessions": 1212,
    "conv_rate": 2.15,
    "net_roas": 5.05,
    "organic_pct": 54.4
  },
  {
    "experiment_id": "TRUTH_OR_DARE_EXACT_BOOST_ACTIVITY",
    "experiment_name": "Truth Or Dare - Exact Games",
    "strategy_id": "EXACT_BOOST",
    "week_start": "2026-01-25",
    "sales": 1405.3,
    "ads_spend": 236.19,
    "total_orders": 47,
    "ads_orders": 25,
    "organic_orders": 22,
    "sessions": 1083,
    "conv_rate": 2.31,
    "net_roas": 4.95,
    "organic_pct": 46.8
  },
  {
    "experiment_id": "TRUTH_OR_DARE_EXACT_BOOST_ACTIVITY",
    "experiment_name": "Truth Or Dare - Exact Games",
    "strategy_id": "EXACT_BOOST",
    "week_start": "2026-02-01",
    "sales": 1584.7,
    "ads_spend": 222.54,
    "total_orders": 52,
    "ads_orders": 32,
    "organic_orders": 20,
    "sessions": 960,
    "conv_rate": 3.33,
    "net_roas": 6.12,
    "organic_pct": 38.5
  },
  {
    "experiment_id": "TRUTH_OR_DARE_EXACT_BOOST_ACTIVITY",
    "experiment_name": "Truth Or Dare - Exact Games",
    "strategy_id": "EXACT_BOOST",
    "week_start": "2026-02-08",
    "sales": 1644.5,
    "ads_spend": 218.99,
    "total_orders": 55,
    "ads_orders": 24,
    "organic_orders": 31,
    "sessions": 867,
    "conv_rate": 2.77,
    "net_roas": 6.51,
    "organic_pct": 56.4
  },
  {
    "experiment_id": "TRUTH_OR_DARE_EXACT_BOOST_ACTIVITY",
    "experiment_name": "Truth Or Dare - Exact Games",
    "strategy_id": "EXACT_BOOST",
    "week_start": "2026-02-15",
    "sales": 837.2,
    "ads_spend": 141.43,
    "total_orders": 28,
    "ads_orders": 18,
    "organic_orders": 10,
    "sessions": 542,
    "conv_rate": 3.32,
    "net_roas": 4.92,
    "organic_pct": 35.7
  },
  {
    "experiment_id": "TRUTH_OR_DARE_EXACT_BOOST_ACTIVITY_HOLIDAY_2025",
    "experiment_name": "Truth Or Dare - Exact Games (Holiday 2025)",
    "strategy_id": "EXACT_BOOST",
    "week_start": "2025-12-14",
    "sales": 2392.0,
    "ads_spend": 122.64,
    "total_orders": 77,
    "ads_orders": 9,
    "organic_orders": 68,
    "sessions": 1318,
    "conv_rate": 0.68,
    "net_roas": 18.5,
    "organic_pct": 88.3
  },
  {
    "experiment_id": "TRUTH_OR_DARE_EXACT_BOOST_ACTIVITY_HOLIDAY_2025",
    "experiment_name": "Truth Or Dare - Exact Games (Holiday 2025)",
    "strategy_id": "EXACT_BOOST",
    "week_start": "2025-12-21",
    "sales": 2093.0,
    "ads_spend": 322.16,
    "total_orders": 69,
    "ads_orders": 27,
    "organic_orders": 42,
    "sessions": 1362,
    "conv_rate": 1.98,
    "net_roas": 5.5,
    "organic_pct": 60.9
  },
  {
    "experiment_id": "TRUTH_OR_DARE_EXACT_BOOST_ACTIVITY_HOLIDAY_2025",
    "experiment_name": "Truth Or Dare - Exact Games (Holiday 2025)",
    "strategy_id": "EXACT_BOOST",
    "week_start": "2025-12-28",
    "sales": 657.8,
    "ads_spend": 190.71,
    "total_orders": 22,
    "ads_orders": 9,
    "organic_orders": 13,
    "sessions": 590,
    "conv_rate": 1.53,
    "net_roas": 2.45,
    "organic_pct": 59.1
  },
  {
    "experiment_id": "TRUTH_OR_DARE_HUNTER_GIFT_GENERAL",
    "experiment_name": "Truth Or Dare - Broad Discovery",
    "strategy_id": "HUNTER",
    "week_start": "2025-12-28",
    "sales": 538.2,
    "ads_spend": 162.77,
    "total_orders": 18,
    "ads_orders": 13,
    "organic_orders": 5,
    "sessions": 527,
    "conv_rate": 2.47,
    "net_roas": 2.31,
    "organic_pct": 27.8
  },
  {
    "experiment_id": "TRUTH_OR_DARE_HUNTER_GIFT_GENERAL",
    "experiment_name": "Truth Or Dare - Broad Discovery",
    "strategy_id": "HUNTER",
    "week_start": "2026-01-04",
    "sales": 2003.3,
    "ads_spend": 586.93,
    "total_orders": 67,
    "ads_orders": 44,
    "organic_orders": 23,
    "sessions": 1568,
    "conv_rate": 2.81,
    "net_roas": 2.41,
    "organic_pct": 34.3
  },
  {
    "experiment_id": "TRUTH_OR_DARE_HUNTER_GIFT_GENERAL",
    "experiment_name": "Truth Or Dare - Broad Discovery",
    "strategy_id": "HUNTER",
    "week_start": "2026-01-11",
    "sales": 1704.3,
    "ads_spend": 276.57,
    "total_orders": 56,
    "ads_orders": 21,
    "organic_orders": 35,
    "sessions": 1275,
    "conv_rate": 1.65,
    "net_roas": 5.16,
    "organic_pct": 62.5
  },
  {
    "experiment_id": "TRUTH_OR_DARE_HUNTER_GIFT_GENERAL",
    "experiment_name": "Truth Or Dare - Broad Discovery",
    "strategy_id": "HUNTER",
    "week_start": "2026-01-18",
    "sales": 1704.3,
    "ads_spend": 281.85,
    "total_orders": 57,
    "ads_orders": 26,
    "organic_orders": 31,
    "sessions": 1212,
    "conv_rate": 2.15,
    "net_roas": 5.05,
    "organic_pct": 54.4
  },
  {
    "experiment_id": "TRUTH_OR_DARE_HUNTER_GIFT_GENERAL",
    "experiment_name": "Truth Or Dare - Broad Discovery",
    "strategy_id": "HUNTER",
    "week_start": "2026-01-25",
    "sales": 1405.3,
    "ads_spend": 236.19,
    "total_orders": 47,
    "ads_orders": 25,
    "organic_orders": 22,
    "sessions": 1083,
    "conv_rate": 2.31,
    "net_roas": 4.95,
    "organic_pct": 46.8
  },
  {
    "experiment_id": "TRUTH_OR_DARE_HUNTER_GIFT_GENERAL",
    "experiment_name": "Truth Or Dare - Broad Discovery",
    "strategy_id": "HUNTER",
    "week_start": "2026-02-01",
    "sales": 1584.7,
    "ads_spend": 222.54,
    "total_orders": 52,
    "ads_orders": 32,
    "organic_orders": 20,
    "sessions": 960,
    "conv_rate": 3.33,
    "net_roas": 6.12,
    "organic_pct": 38.5
  },
  {
    "experiment_id": "TRUTH_OR_DARE_HUNTER_GIFT_GENERAL",
    "experiment_name": "Truth Or Dare - Broad Discovery",
    "strategy_id": "HUNTER",
    "week_start": "2026-02-08",
    "sales": 1644.5,
    "ads_spend": 218.99,
    "total_orders": 55,
    "ads_orders": 24,
    "organic_orders": 31,
    "sessions": 867,
    "conv_rate": 2.77,
    "net_roas": 6.51,
    "organic_pct": 56.4
  },
  {
    "experiment_id": "TRUTH_OR_DARE_HUNTER_GIFT_GENERAL",
    "experiment_name": "Truth Or Dare - Broad Discovery",
    "strategy_id": "HUNTER",
    "week_start": "2026-02-15",
    "sales": 837.2,
    "ads_spend": 141.43,
    "total_orders": 28,
    "ads_orders": 18,
    "organic_orders": 10,
    "sessions": 542,
    "conv_rate": 3.32,
    "net_roas": 4.92,
    "organic_pct": 35.7
  },
  {
    "experiment_id": "TRUTH_OR_DARE_HUNTER_GIFT_GENERAL_HOLIDAY_2025",
    "experiment_name": "Truth Or Dare - Broad Discovery (Holiday 2025)",
    "strategy_id": "HUNTER",
    "week_start": "2025-12-14",
    "sales": 5262.4,
    "ads_spend": 266.64,
    "total_orders": 172,
    "ads_orders": 20,
    "organic_orders": 152,
    "sessions": 2679,
    "conv_rate": 0.75,
    "net_roas": 18.74,
    "organic_pct": 88.4
  },
  {
    "experiment_id": "TRUTH_OR_DARE_HUNTER_GIFT_GENERAL_HOLIDAY_2025",
    "experiment_name": "Truth Or Dare - Broad Discovery (Holiday 2025)",
    "strategy_id": "HUNTER",
    "week_start": "2025-12-21",
    "sales": 2093.0,
    "ads_spend": 322.16,
    "total_orders": 69,
    "ads_orders": 27,
    "organic_orders": 42,
    "sessions": 1362,
    "conv_rate": 1.98,
    "net_roas": 5.5,
    "organic_pct": 60.9
  },
  {
    "experiment_id": "TRUTH_OR_DARE_HUNTER_GIFT_GENERAL_HOLIDAY_2025",
    "experiment_name": "Truth Or Dare - Broad Discovery (Holiday 2025)",
    "strategy_id": "HUNTER",
    "week_start": "2025-12-28",
    "sales": 657.8,
    "ads_spend": 190.71,
    "total_orders": 22,
    "ads_orders": 9,
    "organic_orders": 13,
    "sessions": 590,
    "conv_rate": 1.53,
    "net_roas": 2.45,
    "organic_pct": 59.1
  },
  {
    "experiment_id": "TRUTH_OR_DARE_LOW_COST_DISCOVERY_GIFT_GENERAL",
    "experiment_name": "Truth Or Dare - Auto Discovery",
    "strategy_id": "LOW_COST_DISCOVERY",
    "week_start": "2025-12-28",
    "sales": 538.2,
    "ads_spend": 162.77,
    "total_orders": 18,
    "ads_orders": 13,
    "organic_orders": 5,
    "sessions": 527,
    "conv_rate": 2.47,
    "net_roas": 2.31,
    "organic_pct": 27.8
  },
  {
    "experiment_id": "TRUTH_OR_DARE_LOW_COST_DISCOVERY_GIFT_GENERAL",
    "experiment_name": "Truth Or Dare - Auto Discovery",
    "strategy_id": "LOW_COST_DISCOVERY",
    "week_start": "2026-01-04",
    "sales": 2003.3,
    "ads_spend": 586.93,
    "total_orders": 67,
    "ads_orders": 44,
    "organic_orders": 23,
    "sessions": 1568,
    "conv_rate": 2.81,
    "net_roas": 2.41,
    "organic_pct": 34.3
  },
  {
    "experiment_id": "TRUTH_OR_DARE_LOW_COST_DISCOVERY_GIFT_GENERAL",
    "experiment_name": "Truth Or Dare - Auto Discovery",
    "strategy_id": "LOW_COST_DISCOVERY",
    "week_start": "2026-01-11",
    "sales": 1704.3,
    "ads_spend": 276.57,
    "total_orders": 56,
    "ads_orders": 21,
    "organic_orders": 35,
    "sessions": 1275,
    "conv_rate": 1.65,
    "net_roas": 5.16,
    "organic_pct": 62.5
  },
  {
    "experiment_id": "TRUTH_OR_DARE_LOW_COST_DISCOVERY_GIFT_GENERAL",
    "experiment_name": "Truth Or Dare - Auto Discovery",
    "strategy_id": "LOW_COST_DISCOVERY",
    "week_start": "2026-01-18",
    "sales": 1704.3,
    "ads_spend": 281.85,
    "total_orders": 57,
    "ads_orders": 26,
    "organic_orders": 31,
    "sessions": 1212,
    "conv_rate": 2.15,
    "net_roas": 5.05,
    "organic_pct": 54.4
  },
  {
    "experiment_id": "TRUTH_OR_DARE_LOW_COST_DISCOVERY_GIFT_GENERAL",
    "experiment_name": "Truth Or Dare - Auto Discovery",
    "strategy_id": "LOW_COST_DISCOVERY",
    "week_start": "2026-01-25",
    "sales": 1405.3,
    "ads_spend": 236.19,
    "total_orders": 47,
    "ads_orders": 25,
    "organic_orders": 22,
    "sessions": 1083,
    "conv_rate": 2.31,
    "net_roas": 4.95,
    "organic_pct": 46.8
  },
  {
    "experiment_id": "TRUTH_OR_DARE_LOW_COST_DISCOVERY_GIFT_GENERAL",
    "experiment_name": "Truth Or Dare - Auto Discovery",
    "strategy_id": "LOW_COST_DISCOVERY",
    "week_start": "2026-02-01",
    "sales": 1584.7,
    "ads_spend": 222.54,
    "total_orders": 52,
    "ads_orders": 35,
    "organic_orders": 17,
    "sessions": 960,
    "conv_rate": 3.65,
    "net_roas": 6.12,
    "organic_pct": 32.7
  },
  {
    "experiment_id": "TRUTH_OR_DARE_LOW_COST_DISCOVERY_GIFT_GENERAL",
    "experiment_name": "Truth Or Dare - Auto Discovery",
    "strategy_id": "LOW_COST_DISCOVERY",
    "week_start": "2026-02-08",
    "sales": 1644.5,
    "ads_spend": 218.47,
    "total_orders": 55,
    "ads_orders": 25,
    "organic_orders": 30,
    "sessions": 867,
    "conv_rate": 2.88,
    "net_roas": 6.53,
    "organic_pct": 54.5
  },
  {
    "experiment_id": "TRUTH_OR_DARE_LOW_COST_DISCOVERY_GIFT_GENERAL",
    "experiment_name": "Truth Or Dare - Auto Discovery",
    "strategy_id": "LOW_COST_DISCOVERY",
    "week_start": "2026-02-15",
    "sales": 1166.1,
    "ads_spend": 159.76,
    "total_orders": 39,
    "ads_orders": 18,
    "organic_orders": 21,
    "sessions": 850,
    "conv_rate": 2.12,
    "net_roas": 6.3,
    "organic_pct": 53.8
  },
  {
    "experiment_id": "TRUTH_OR_DARE_LOW_COST_DISCOVERY_GIFT_GENERAL",
    "experiment_name": "Truth Or Dare - Auto Discovery",
    "strategy_id": "LOW_COST_DISCOVERY",
    "week_start": "2026-02-22",
    "sales": 807.3,
    "ads_spend": 321.47,
    "total_orders": 27,
    "ads_orders": 18,
    "organic_orders": 9,
    "sessions": 975,
    "conv_rate": 1.85,
    "net_roas": 1.51,
    "organic_pct": 33.3
  },
  {
    "experiment_id": "TRUTH_OR_DARE_LOW_COST_DISCOVERY_GIFT_GENERAL",
    "experiment_name": "Truth Or Dare - Auto Discovery",
    "strategy_id": "LOW_COST_DISCOVERY",
    "week_start": "2026-03-01",
    "sales": 747.5,
    "ads_spend": 231.51,
    "total_orders": 25,
    "ads_orders": 18,
    "organic_orders": 7,
    "sessions": 570,
    "conv_rate": 3.16,
    "net_roas": 2.23,
    "organic_pct": 28.0
  },
  {
    "experiment_id": "TRUTH_OR_DARE_LOW_COST_DISCOVERY_GIFT_GENERAL_HOLIDAY_2025",
    "experiment_name": "Truth Or Dare - Auto Discovery (Holiday 2025)",
    "strategy_id": "LOW_COST_DISCOVERY",
    "week_start": "2025-12-14",
    "sales": 687.7,
    "ads_spend": 40.77,
    "total_orders": 21,
    "ads_orders": 4,
    "organic_orders": 17,
    "sessions": 334,
    "conv_rate": 1.2,
    "net_roas": 15.87,
    "organic_pct": 81.0
  },
  {
    "experiment_id": "TRUTH_OR_DARE_LOW_COST_DISCOVERY_GIFT_GENERAL_HOLIDAY_2025",
    "experiment_name": "Truth Or Dare - Auto Discovery (Holiday 2025)",
    "strategy_id": "LOW_COST_DISCOVERY",
    "week_start": "2025-12-21",
    "sales": 2093.0,
    "ads_spend": 322.16,
    "total_orders": 69,
    "ads_orders": 27,
    "organic_orders": 42,
    "sessions": 1362,
    "conv_rate": 1.98,
    "net_roas": 5.5,
    "organic_pct": 60.9
  },
  {
    "experiment_id": "TRUTH_OR_DARE_LOW_COST_DISCOVERY_GIFT_GENERAL_HOLIDAY_2025",
    "experiment_name": "Truth Or Dare - Auto Discovery (Holiday 2025)",
    "strategy_id": "LOW_COST_DISCOVERY",
    "week_start": "2025-12-28",
    "sales": 657.8,
    "ads_spend": 190.71,
    "total_orders": 22,
    "ads_orders": 9,
    "organic_orders": 13,
    "sessions": 590,
    "conv_rate": 1.53,
    "net_roas": 2.45,
    "organic_pct": 59.1
  },
  {
    "experiment_id": "WHITE_LOLLIBOX_CATEGORY_CONQUEST_GIFT_GENERAL",
    "experiment_name": "White Lollibox - Copycat Conquest",
    "strategy_id": "CATEGORY_CONQUEST",
    "week_start": "2025-12-28",
    "sales": 3536.0,
    "ads_spend": 723.35,
    "total_orders": 64,
    "ads_orders": 38,
    "organic_orders": 26,
    "sessions": 3194,
    "conv_rate": 1.19,
    "net_roas": 3.89,
    "organic_pct": 40.6
  },
  {
    "experiment_id": "WHITE_LOLLIBOX_CATEGORY_CONQUEST_GIFT_GENERAL",
    "experiment_name": "White Lollibox - Copycat Conquest",
    "strategy_id": "CATEGORY_CONQUEST",
    "week_start": "2026-01-04",
    "sales": 10270.72,
    "ads_spend": 2434.71,
    "total_orders": 187,
    "ads_orders": 112,
    "organic_orders": 75,
    "sessions": 9365,
    "conv_rate": 1.2,
    "net_roas": 3.22,
    "organic_pct": 40.1
  },
  {
    "experiment_id": "WHITE_LOLLIBOX_CATEGORY_CONQUEST_GIFT_GENERAL",
    "experiment_name": "White Lollibox - Copycat Conquest",
    "strategy_id": "CATEGORY_CONQUEST",
    "week_start": "2026-01-11",
    "sales": 9996.0,
    "ads_spend": 2174.47,
    "total_orders": 173,
    "ads_orders": 99,
    "organic_orders": 74,
    "sessions": 8521,
    "conv_rate": 1.16,
    "net_roas": 3.6,
    "organic_pct": 42.8
  },
  {
    "experiment_id": "WHITE_LOLLIBOX_CATEGORY_CONQUEST_GIFT_GENERAL",
    "experiment_name": "White Lollibox - Copycat Conquest",
    "strategy_id": "CATEGORY_CONQUEST",
    "week_start": "2026-01-18",
    "sales": 9408.48,
    "ads_spend": 2010.8,
    "total_orders": 167,
    "ads_orders": 107,
    "organic_orders": 60,
    "sessions": 8700,
    "conv_rate": 1.23,
    "net_roas": 3.68,
    "organic_pct": 35.9
  },
  {
    "experiment_id": "WHITE_LOLLIBOX_CATEGORY_CONQUEST_GIFT_GENERAL",
    "experiment_name": "White Lollibox - Copycat Conquest",
    "strategy_id": "CATEGORY_CONQUEST",
    "week_start": "2026-01-25",
    "sales": 10656.96,
    "ads_spend": 1729.63,
    "total_orders": 146,
    "ads_orders": 85,
    "organic_orders": 61,
    "sessions": 9082,
    "conv_rate": 0.94,
    "net_roas": 5.16,
    "organic_pct": 41.8
  },
  {
    "experiment_id": "WHITE_LOLLIBOX_CATEGORY_CONQUEST_GIFT_GENERAL",
    "experiment_name": "White Lollibox - Copycat Conquest",
    "strategy_id": "CATEGORY_CONQUEST",
    "week_start": "2026-02-01",
    "sales": 9786.56,
    "ads_spend": 1636.07,
    "total_orders": 177,
    "ads_orders": 113,
    "organic_orders": 64,
    "sessions": 8078,
    "conv_rate": 1.4,
    "net_roas": 4.98,
    "organic_pct": 36.2
  },
  {
    "experiment_id": "WHITE_LOLLIBOX_CATEGORY_CONQUEST_GIFT_GENERAL",
    "experiment_name": "White Lollibox - Copycat Conquest",
    "strategy_id": "CATEGORY_CONQUEST",
    "week_start": "2026-02-08",
    "sales": 8744.8,
    "ads_spend": 1980.34,
    "total_orders": 155,
    "ads_orders": 111,
    "organic_orders": 44,
    "sessions": 7419,
    "conv_rate": 1.5,
    "net_roas": 3.42,
    "organic_pct": 28.4
  },
  {
    "experiment_id": "WHITE_LOLLIBOX_CATEGORY_CONQUEST_GIFT_GENERAL",
    "experiment_name": "White Lollibox - Copycat Conquest",
    "strategy_id": "CATEGORY_CONQUEST",
    "week_start": "2026-02-15",
    "sales": 4836.16,
    "ads_spend": 1141.68,
    "total_orders": 89,
    "ads_orders": 53,
    "organic_orders": 36,
    "sessions": 3340,
    "conv_rate": 1.59,
    "net_roas": 3.24,
    "organic_pct": 40.4
  },
  {
    "experiment_id": "WHITE_LOLLIBOX_EXACT_BOOST_GIFT_TEEN",
    "experiment_name": "White Lollibox - Exact Teen",
    "strategy_id": "EXACT_BOOST",
    "week_start": "2025-12-28",
    "sales": 2230.4,
    "ads_spend": 582.22,
    "total_orders": 40,
    "ads_orders": 31,
    "organic_orders": 9,
    "sessions": 1915,
    "conv_rate": 1.62,
    "net_roas": 2.83,
    "organic_pct": 22.5
  },
  {
    "experiment_id": "WHITE_LOLLIBOX_EXACT_BOOST_GIFT_TEEN",
    "experiment_name": "White Lollibox - Exact Teen",
    "strategy_id": "EXACT_BOOST",
    "week_start": "2026-01-04",
    "sales": 6245.12,
    "ads_spend": 2045.38,
    "total_orders": 115,
    "ads_orders": 90,
    "organic_orders": 25,
    "sessions": 5427,
    "conv_rate": 1.66,
    "net_roas": 2.05,
    "organic_pct": 21.7
  },
  {
    "experiment_id": "WHITE_LOLLIBOX_EXACT_BOOST_GIFT_TEEN",
    "experiment_name": "White Lollibox - Exact Teen",
    "strategy_id": "EXACT_BOOST",
    "week_start": "2026-01-11",
    "sales": 6027.52,
    "ads_spend": 1920.3,
    "total_orders": 103,
    "ads_orders": 78,
    "organic_orders": 25,
    "sessions": 5172,
    "conv_rate": 1.51,
    "net_roas": 2.14,
    "organic_pct": 24.3
  },
  {
    "experiment_id": "WHITE_LOLLIBOX_EXACT_BOOST_GIFT_TEEN",
    "experiment_name": "White Lollibox - Exact Teen",
    "strategy_id": "EXACT_BOOST",
    "week_start": "2026-01-18",
    "sales": 6525.28,
    "ads_spend": 1696.04,
    "total_orders": 114,
    "ads_orders": 90,
    "organic_orders": 24,
    "sessions": 5282,
    "conv_rate": 1.7,
    "net_roas": 2.85,
    "organic_pct": 21.1
  },
  {
    "experiment_id": "WHITE_LOLLIBOX_EXACT_BOOST_GIFT_TEEN",
    "experiment_name": "White Lollibox - Exact Teen",
    "strategy_id": "EXACT_BOOST",
    "week_start": "2026-01-25",
    "sales": 7395.68,
    "ads_spend": 1294.37,
    "total_orders": 89,
    "ads_orders": 59,
    "organic_orders": 30,
    "sessions": 4946,
    "conv_rate": 1.19,
    "net_roas": 4.71,
    "organic_pct": 33.7
  },
  {
    "experiment_id": "WHITE_LOLLIBOX_EXACT_BOOST_GIFT_TEEN",
    "experiment_name": "White Lollibox - Exact Teen",
    "strategy_id": "EXACT_BOOST",
    "week_start": "2026-02-01",
    "sales": 5818.08,
    "ads_spend": 1273.98,
    "total_orders": 105,
    "ads_orders": 88,
    "organic_orders": 17,
    "sessions": 4645,
    "conv_rate": 1.89,
    "net_roas": 3.57,
    "organic_pct": 16.2
  },
  {
    "experiment_id": "WHITE_LOLLIBOX_EXACT_BOOST_GIFT_TEEN",
    "experiment_name": "White Lollibox - Exact Teen",
    "strategy_id": "EXACT_BOOST",
    "week_start": "2026-02-08",
    "sales": 5646.72,
    "ads_spend": 1602.47,
    "total_orders": 98,
    "ads_orders": 86,
    "organic_orders": 12,
    "sessions": 4475,
    "conv_rate": 1.92,
    "net_roas": 2.52,
    "organic_pct": 12.2
  },
  {
    "experiment_id": "WHITE_LOLLIBOX_EXACT_BOOST_GIFT_TEEN",
    "experiment_name": "White Lollibox - Exact Teen",
    "strategy_id": "EXACT_BOOST",
    "week_start": "2026-02-15",
    "sales": 2714.56,
    "ads_spend": 783.74,
    "total_orders": 50,
    "ads_orders": 32,
    "organic_orders": 18,
    "sessions": 1965,
    "conv_rate": 1.63,
    "net_roas": 2.46,
    "organic_pct": 36.0
  },
  {
    "experiment_id": "WHITE_LOLLIBOX_EXACT_BOOST_GIFT_TEEN_HOLIDAY_2025",
    "experiment_name": "White Lollibox - Exact Teen (Holiday 2025)",
    "strategy_id": "EXACT_BOOST",
    "week_start": "2025-12-14",
    "sales": 67855.84,
    "ads_spend": 10898.8,
    "total_orders": 1213,
    "ads_orders": 728,
    "organic_orders": 485,
    "sessions": 34063,
    "conv_rate": 2.14,
    "net_roas": 5.23,
    "organic_pct": 40.0
  },
  {
    "experiment_id": "WHITE_LOLLIBOX_EXACT_BOOST_GIFT_TEEN_HOLIDAY_2025",
    "experiment_name": "White Lollibox - Exact Teen (Holiday 2025)",
    "strategy_id": "EXACT_BOOST",
    "week_start": "2025-12-21",
    "sales": 25644.16,
    "ads_spend": 6506.16,
    "total_orders": 452,
    "ads_orders": 318,
    "organic_orders": 134,
    "sessions": 11619,
    "conv_rate": 2.74,
    "net_roas": 2.94,
    "organic_pct": 29.6
  },
  {
    "experiment_id": "WHITE_LOLLIBOX_EXACT_BOOST_GIFT_TEEN_HOLIDAY_2025",
    "experiment_name": "White Lollibox - Exact Teen (Holiday 2025)",
    "strategy_id": "EXACT_BOOST",
    "week_start": "2025-12-28",
    "sales": 3370.08,
    "ads_spend": 910.21,
    "total_orders": 59,
    "ads_orders": 29,
    "organic_orders": 30,
    "sessions": 2370,
    "conv_rate": 1.22,
    "net_roas": 2.7,
    "organic_pct": 50.8
  },
  {
    "experiment_id": "WHITE_LOLLIBOX_HUNTER_GIFT_GENERAL",
    "experiment_name": "White Lollibox - Broad Gift Discovery",
    "strategy_id": "HUNTER",
    "week_start": "2025-12-28",
    "sales": 3522.37,
    "ads_spend": 1137.33,
    "total_orders": 75,
    "ads_orders": 73,
    "organic_orders": 2,
    "sessions": 2712,
    "conv_rate": 2.69,
    "net_roas": 2.1,
    "organic_pct": 2.7
  },
  {
    "experiment_id": "WHITE_LOLLIBOX_HUNTER_GIFT_GENERAL",
    "experiment_name": "White Lollibox - Broad Gift Discovery",
    "strategy_id": "HUNTER",
    "week_start": "2026-01-04",
    "sales": 8894.15,
    "ads_spend": 3408.69,
    "total_orders": 195,
    "ads_orders": 192,
    "organic_orders": 3,
    "sessions": 7260,
    "conv_rate": 2.64,
    "net_roas": 1.61,
    "organic_pct": 1.5
  },
  {
    "experiment_id": "WHITE_LOLLIBOX_HUNTER_GIFT_GENERAL",
    "experiment_name": "White Lollibox - Broad Gift Discovery",
    "strategy_id": "HUNTER",
    "week_start": "2026-01-11",
    "sales": 9796.46,
    "ads_spend": 3103.36,
    "total_orders": 208,
    "ads_orders": 181,
    "organic_orders": 27,
    "sessions": 7520,
    "conv_rate": 2.41,
    "net_roas": 2.16,
    "organic_pct": 13.0
  },
  {
    "experiment_id": "WHITE_LOLLIBOX_HUNTER_GIFT_GENERAL",
    "experiment_name": "White Lollibox - Broad Gift Discovery",
    "strategy_id": "HUNTER",
    "week_start": "2026-01-18",
    "sales": 9317.85,
    "ads_spend": 3090.1,
    "total_orders": 198,
    "ads_orders": 195,
    "organic_orders": 3,
    "sessions": 7787,
    "conv_rate": 2.5,
    "net_roas": 2.02,
    "organic_pct": 1.5
  },
  {
    "experiment_id": "WHITE_LOLLIBOX_HUNTER_GIFT_GENERAL",
    "experiment_name": "White Lollibox - Broad Gift Discovery",
    "strategy_id": "HUNTER",
    "week_start": "2026-01-25",
    "sales": 9806.19,
    "ads_spend": 2441.55,
    "total_orders": 161,
    "ads_orders": 126,
    "organic_orders": 35,
    "sessions": 6815,
    "conv_rate": 1.85,
    "net_roas": 3.02,
    "organic_pct": 21.7
  },
  {
    "experiment_id": "WHITE_LOLLIBOX_HUNTER_GIFT_GENERAL",
    "experiment_name": "White Lollibox - Broad Gift Discovery",
    "strategy_id": "HUNTER",
    "week_start": "2026-02-01",
    "sales": 8368.14,
    "ads_spend": 1983.68,
    "total_orders": 179,
    "ads_orders": 157,
    "organic_orders": 22,
    "sessions": 6249,
    "conv_rate": 2.51,
    "net_roas": 3.22,
    "organic_pct": 12.3
  },
  {
    "experiment_id": "WHITE_LOLLIBOX_HUNTER_GIFT_GENERAL",
    "experiment_name": "White Lollibox - Broad Gift Discovery",
    "strategy_id": "HUNTER",
    "week_start": "2026-02-08",
    "sales": 8635.48,
    "ads_spend": 2275.77,
    "total_orders": 185,
    "ads_orders": 176,
    "organic_orders": 9,
    "sessions": 5957,
    "conv_rate": 2.95,
    "net_roas": 2.79,
    "organic_pct": 4.9
  },
  {
    "experiment_id": "WHITE_LOLLIBOX_HUNTER_GIFT_GENERAL",
    "experiment_name": "White Lollibox - Broad Gift Discovery",
    "strategy_id": "HUNTER",
    "week_start": "2026-02-15",
    "sales": 6079.65,
    "ads_spend": 1666.21,
    "total_orders": 142,
    "ads_orders": 117,
    "organic_orders": 25,
    "sessions": 4691,
    "conv_rate": 2.49,
    "net_roas": 2.65,
    "organic_pct": 17.6
  },
  {
    "experiment_id": "WHITE_LOLLIBOX_HUNTER_GIFT_GENERAL",
    "experiment_name": "White Lollibox - Broad Gift Discovery",
    "strategy_id": "HUNTER",
    "week_start": "2026-02-22",
    "sales": 6456.84,
    "ads_spend": 2199.1,
    "total_orders": 151,
    "ads_orders": 168,
    "organic_orders": -17,
    "sessions": 4729,
    "conv_rate": 3.55,
    "net_roas": 1.94,
    "organic_pct": -11.3
  },
  {
    "experiment_id": "WHITE_LOLLIBOX_HUNTER_GIFT_GENERAL",
    "experiment_name": "White Lollibox - Broad Gift Discovery",
    "strategy_id": "HUNTER",
    "week_start": "2026-03-01",
    "sales": 7641.28,
    "ads_spend": 1894.05,
    "total_orders": 166,
    "ads_orders": 110,
    "organic_orders": 56,
    "sessions": 4545,
    "conv_rate": 2.42,
    "net_roas": 3.03,
    "organic_pct": 33.7
  },
  {
    "experiment_id": "WHITE_LOLLIBOX_LOW_COST_DISCOVERY_GIFT_GENERAL",
    "experiment_name": "White Lollibox - Auto Discovery",
    "strategy_id": "LOW_COST_DISCOVERY",
    "week_start": "2025-12-28",
    "sales": 2230.4,
    "ads_spend": 582.22,
    "total_orders": 40,
    "ads_orders": 31,
    "organic_orders": 9,
    "sessions": 1915,
    "conv_rate": 1.62,
    "net_roas": 2.83,
    "organic_pct": 22.5
  },
  {
    "experiment_id": "WHITE_LOLLIBOX_LOW_COST_DISCOVERY_GIFT_GENERAL",
    "experiment_name": "White Lollibox - Auto Discovery",
    "strategy_id": "LOW_COST_DISCOVERY",
    "week_start": "2026-01-04",
    "sales": 6245.12,
    "ads_spend": 2045.38,
    "total_orders": 115,
    "ads_orders": 90,
    "organic_orders": 25,
    "sessions": 5427,
    "conv_rate": 1.66,
    "net_roas": 2.05,
    "organic_pct": 21.7
  },
  {
    "experiment_id": "WHITE_LOLLIBOX_LOW_COST_DISCOVERY_GIFT_GENERAL",
    "experiment_name": "White Lollibox - Auto Discovery",
    "strategy_id": "LOW_COST_DISCOVERY",
    "week_start": "2026-01-11",
    "sales": 6027.52,
    "ads_spend": 1920.3,
    "total_orders": 103,
    "ads_orders": 78,
    "organic_orders": 25,
    "sessions": 5172,
    "conv_rate": 1.51,
    "net_roas": 2.14,
    "organic_pct": 24.3
  },
  {
    "experiment_id": "WHITE_LOLLIBOX_LOW_COST_DISCOVERY_GIFT_GENERAL",
    "experiment_name": "White Lollibox - Auto Discovery",
    "strategy_id": "LOW_COST_DISCOVERY",
    "week_start": "2026-01-18",
    "sales": 6525.28,
    "ads_spend": 1696.04,
    "total_orders": 114,
    "ads_orders": 90,
    "organic_orders": 24,
    "sessions": 5282,
    "conv_rate": 1.7,
    "net_roas": 2.85,
    "organic_pct": 21.1
  },
  {
    "experiment_id": "WHITE_LOLLIBOX_LOW_COST_DISCOVERY_GIFT_GENERAL",
    "experiment_name": "White Lollibox - Auto Discovery",
    "strategy_id": "LOW_COST_DISCOVERY",
    "week_start": "2026-01-25",
    "sales": 7395.68,
    "ads_spend": 1294.37,
    "total_orders": 89,
    "ads_orders": 59,
    "organic_orders": 30,
    "sessions": 4946,
    "conv_rate": 1.19,
    "net_roas": 4.71,
    "organic_pct": 33.7
  },
  {
    "experiment_id": "WHITE_LOLLIBOX_LOW_COST_DISCOVERY_GIFT_GENERAL",
    "experiment_name": "White Lollibox - Auto Discovery",
    "strategy_id": "LOW_COST_DISCOVERY",
    "week_start": "2026-02-01",
    "sales": 5818.08,
    "ads_spend": 1273.98,
    "total_orders": 105,
    "ads_orders": 88,
    "organic_orders": 17,
    "sessions": 4645,
    "conv_rate": 1.89,
    "net_roas": 3.57,
    "organic_pct": 16.2
  },
  {
    "experiment_id": "WHITE_LOLLIBOX_LOW_COST_DISCOVERY_GIFT_GENERAL",
    "experiment_name": "White Lollibox - Auto Discovery",
    "strategy_id": "LOW_COST_DISCOVERY",
    "week_start": "2026-02-08",
    "sales": 5646.72,
    "ads_spend": 1598.77,
    "total_orders": 98,
    "ads_orders": 87,
    "organic_orders": 11,
    "sessions": 4475,
    "conv_rate": 1.94,
    "net_roas": 2.53,
    "organic_pct": 11.2
  },
  {
    "experiment_id": "WHITE_LOLLIBOX_LOW_COST_DISCOVERY_GIFT_GENERAL",
    "experiment_name": "White Lollibox - Auto Discovery",
    "strategy_id": "LOW_COST_DISCOVERY",
    "week_start": "2026-02-15",
    "sales": 3419.04,
    "ads_spend": 901.81,
    "total_orders": 63,
    "ads_orders": 42,
    "organic_orders": 21,
    "sessions": 3286,
    "conv_rate": 1.28,
    "net_roas": 2.79,
    "organic_pct": 33.3
  },
  {
    "experiment_id": "WHITE_LOLLIBOX_LOW_COST_DISCOVERY_GIFT_GENERAL",
    "experiment_name": "White Lollibox - Auto Discovery",
    "strategy_id": "LOW_COST_DISCOVERY",
    "week_start": "2026-02-22",
    "sales": 3367.36,
    "ads_spend": 1231.99,
    "total_orders": 60,
    "ads_orders": 62,
    "organic_orders": -2,
    "sessions": 3436,
    "conv_rate": 1.8,
    "net_roas": 1.73,
    "organic_pct": -3.3
  },
  {
    "experiment_id": "WHITE_LOLLIBOX_LOW_COST_DISCOVERY_GIFT_GENERAL",
    "experiment_name": "White Lollibox - Auto Discovery",
    "strategy_id": "LOW_COST_DISCOVERY",
    "week_start": "2026-03-01",
    "sales": 4131.68,
    "ads_spend": 1339.68,
    "total_orders": 72,
    "ads_orders": 68,
    "organic_orders": 4,
    "sessions": 2707,
    "conv_rate": 2.51,
    "net_roas": 2.08,
    "organic_pct": 5.6
  },
  {
    "experiment_id": "WHITE_LOLLIBOX_LOW_COST_DISCOVERY_GIFT_GENERAL_HOLIDAY_2025",
    "experiment_name": "White Lollibox - Auto Discovery (Holiday 2025)",
    "strategy_id": "LOW_COST_DISCOVERY",
    "week_start": "2025-12-14",
    "sales": 67855.84,
    "ads_spend": 10898.8,
    "total_orders": 1213,
    "ads_orders": 728,
    "organic_orders": 485,
    "sessions": 34063,
    "conv_rate": 2.14,
    "net_roas": 5.23,
    "organic_pct": 40.0
  },
  {
    "experiment_id": "WHITE_LOLLIBOX_LOW_COST_DISCOVERY_GIFT_GENERAL_HOLIDAY_2025",
    "experiment_name": "White Lollibox - Auto Discovery (Holiday 2025)",
    "strategy_id": "LOW_COST_DISCOVERY",
    "week_start": "2025-12-21",
    "sales": 25644.16,
    "ads_spend": 6506.16,
    "total_orders": 452,
    "ads_orders": 318,
    "organic_orders": 134,
    "sessions": 11619,
    "conv_rate": 2.74,
    "net_roas": 2.94,
    "organic_pct": 29.6
  },
  {
    "experiment_id": "WHITE_LOLLIBOX_LOW_COST_DISCOVERY_GIFT_GENERAL_HOLIDAY_2025",
    "experiment_name": "White Lollibox - Auto Discovery (Holiday 2025)",
    "strategy_id": "LOW_COST_DISCOVERY",
    "week_start": "2025-12-28",
    "sales": 3370.08,
    "ads_spend": 910.21,
    "total_orders": 59,
    "ads_orders": 29,
    "organic_orders": 30,
    "sessions": 2370,
    "conv_rate": 1.22,
    "net_roas": 2.7,
    "organic_pct": 50.8
  }
]